<?xml version="1.0" encoding="utf-8"?>
<TransXChange xmlns:xsi="http://www.w3.org/2001/XMLSchema-instance" xmlns:xsd="http://www.w3.org/2001/XMLSchema" xsi:schemaLocation="http://www.transxchange.org.uk/ http://www.transxchange.org.uk/schema/2.1/TransXChange_general.xsd" CreationDateTime="2019-10-07T13:21:00-00:00" ModificationDateTime="2019-10-07T13:21:00-00:00" Modification="new" RevisionNumber="0" FileName="SVRAGAK020.xml" SchemaVersion="2.1" RegistrationDocument="false" xmlns="http://www.transxchange.org.uk/">
  <ServicedOrganisations>
    <ServicedOrganisation>
      <OrganisationCode>160</OrganisationCode>
      <Name>
QE0 : BUS.CIF
</Name>
      <WorkingDays>
        <DateRange>
          <StartDate>2019-10-05</StartDate>
          <EndDate>2019-10-20</EndDate>
        </DateRange>
        <DateRange>
          <StartDate>2019-12-04</StartDate>
          <EndDate>2019-12-08</EndDate>
        </DateRange>
        <DateRange>
          <StartDate>2019-12-21</StartDate>
          <EndDate>2020-01-05</EndDate>
        </DateRange>
        <DateRange>
          <StartDate>2020-02-13</StartDate>
          <EndDate>2020-02-17</EndDate>
        </DateRange>
        <DateRange>
          <StartDate>2020-04-04</StartDate>
          <EndDate>2020-04-19</EndDate>
        </DateRange>
        <DateRange>
          <StartDate>2020-05-02</StartDate>
          <EndDate>2020-05-04</EndDate>
        </DateRange>
        <DateRange>
          <StartDate>2020-05-23</StartDate>
          <EndDate>2020-05-25</EndDate>
        </DateRange>
        <DateRange>
          <StartDate>2020-06-27</StartDate>
          <EndDate>2049-12-31</EndDate>
        </DateRange>
      </WorkingDays>
    </ServicedOrganisation>
  </ServicedOrganisations>
  <StopPoints>
    <AnnotatedStopPointRef>
      <StopPointRef>6490IM1880</StopPointRef>
      <CommonName>Newbarns Road End</CommonName>
    </AnnotatedStopPointRef>
    <AnnotatedStopPointRef>
      <StopPointRef>6490IM009</StopPointRef>
      <CommonName>Old Hotel</CommonName>
    </AnnotatedStopPointRef>
    <AnnotatedStopPointRef>
      <StopPointRef>6490IM1886</StopPointRef>
      <CommonName>Bogindollo Farm Cottages</CommonName>
    </AnnotatedStopPointRef>
    <AnnotatedStopPointRef>
      <StopPointRef>6490IM1716</StopPointRef>
      <CommonName>Bogindollo Road End</CommonName>
    </AnnotatedStopPointRef>
    <AnnotatedStopPointRef>
      <StopPointRef>6490IM018</StopPointRef>
      <CommonName>Finavon Hotel</CommonName>
    </AnnotatedStopPointRef>
    <AnnotatedStopPointRef>
      <StopPointRef>6490IM920</StopPointRef>
      <CommonName>Cadger Path</CommonName>
    </AnnotatedStopPointRef>
    <AnnotatedStopPointRef>
      <StopPointRef>6490IM185</StopPointRef>
      <CommonName>Manse Lane</CommonName>
    </AnnotatedStopPointRef>
    <AnnotatedStopPointRef>
      <StopPointRef>6490IM1832</StopPointRef>
      <CommonName>Fidlerswell</CommonName>
    </AnnotatedStopPointRef>
    <AnnotatedStopPointRef>
      <StopPointRef>6490IM1827</StopPointRef>
      <CommonName>Meikle Coull Road End</CommonName>
    </AnnotatedStopPointRef>
    <AnnotatedStopPointRef>
      <StopPointRef>6490IM1829</StopPointRef>
      <CommonName>Miltonbank Road End</CommonName>
    </AnnotatedStopPointRef>
    <AnnotatedStopPointRef>
      <StopPointRef>6490IM068</StopPointRef>
      <CommonName>Road End</CommonName>
    </AnnotatedStopPointRef>
    <AnnotatedStopPointRef>
      <StopPointRef>6490IM989</StopPointRef>
      <CommonName>Shielhill Bridge Cottage</CommonName>
    </AnnotatedStopPointRef>
    <AnnotatedStopPointRef>
      <StopPointRef>6490IM18889</StopPointRef>
      <CommonName>Crieff Terrace</CommonName>
    </AnnotatedStopPointRef>
    <AnnotatedStopPointRef>
      <StopPointRef>6490IM987</StopPointRef>
      <CommonName>Easthill Road</CommonName>
    </AnnotatedStopPointRef>
    <AnnotatedStopPointRef>
      <StopPointRef>6490IM763</StopPointRef>
      <CommonName>Airlie Place</CommonName>
    </AnnotatedStopPointRef>
    <AnnotatedStopPointRef>
      <StopPointRef>6490IM642</StopPointRef>
      <CommonName>Woodville Inn</CommonName>
    </AnnotatedStopPointRef>
    <AnnotatedStopPointRef>
      <StopPointRef>6490IM918</StopPointRef>
      <CommonName>Northmuir Primary School</CommonName>
    </AnnotatedStopPointRef>
    <AnnotatedStopPointRef>
      <StopPointRef>6490IM643</StopPointRef>
      <CommonName>Hillrise</CommonName>
    </AnnotatedStopPointRef>
    <AnnotatedStopPointRef>
      <StopPointRef>6490IM766</StopPointRef>
      <CommonName>McGregor's Land</CommonName>
    </AnnotatedStopPointRef>
    <AnnotatedStopPointRef>
      <StopPointRef>6490IM481</StopPointRef>
      <CommonName>Post Office</CommonName>
    </AnnotatedStopPointRef>
    <AnnotatedStopPointRef>
      <StopPointRef>6490IM271</StopPointRef>
      <CommonName>Bank Street</CommonName>
    </AnnotatedStopPointRef>
    <AnnotatedStopPointRef>
      <StopPointRef>6490IM1008</StopPointRef>
      <CommonName>St. Andrew's Church</CommonName>
    </AnnotatedStopPointRef>
    <AnnotatedStopPointRef>
      <StopPointRef>6490IM450</StopPointRef>
      <CommonName>Duthie Street</CommonName>
    </AnnotatedStopPointRef>
    <AnnotatedStopPointRef>
      <StopPointRef>6490IM901</StopPointRef>
      <CommonName>Webster's High School</CommonName>
    </AnnotatedStopPointRef>
    <AnnotatedStopPointRef>
      <StopPointRef>6490IM1009</StopPointRef>
      <CommonName>St. Andrew's Church</CommonName>
    </AnnotatedStopPointRef>
    <AnnotatedStopPointRef>
      <StopPointRef>6490IM55</StopPointRef>
      <CommonName>High Street</CommonName>
    </AnnotatedStopPointRef>
    <AnnotatedStopPointRef>
      <StopPointRef>6490IM1021</StopPointRef>
      <CommonName>Cemetery Road</CommonName>
    </AnnotatedStopPointRef>
    <AnnotatedStopPointRef>
      <StopPointRef>6490IM1955</StopPointRef>
      <CommonName>Kilnhill</CommonName>
    </AnnotatedStopPointRef>
  </StopPoints>
  <RouteSections>
    <RouteSection id="AGAK020_001">
      <RouteLink id="AGAK020_001_30519">
        <From>
          <StopPointRef>6490IM1880</StopPointRef>
        </From>
        <To>
          <StopPointRef>6490IM009</StopPointRef>
        </To>
        <Direction>inbound</Direction>
      </RouteLink>
      <RouteLink id="AGAK020_001_30520">
        <From>
          <StopPointRef>6490IM009</StopPointRef>
        </From>
        <To>
          <StopPointRef>6490IM1886</StopPointRef>
        </To>
        <Direction>inbound</Direction>
      </RouteLink>
      <RouteLink id="AGAK020_001_30521">
        <From>
          <StopPointRef>6490IM1886</StopPointRef>
        </From>
        <To>
          <StopPointRef>6490IM1716</StopPointRef>
        </To>
        <Direction>inbound</Direction>
      </RouteLink>
      <RouteLink id="AGAK020_001_30522">
        <From>
          <StopPointRef>6490IM1716</StopPointRef>
        </From>
        <To>
          <StopPointRef>6490IM018</StopPointRef>
        </To>
        <Direction>inbound</Direction>
      </RouteLink>
      <RouteLink id="AGAK020_001_30523">
        <From>
          <StopPointRef>6490IM018</StopPointRef>
        </From>
        <To>
          <StopPointRef>6490IM920</StopPointRef>
        </To>
        <Direction>inbound</Direction>
      </RouteLink>
      <RouteLink id="AGAK020_001_30524">
        <From>
          <StopPointRef>6490IM920</StopPointRef>
        </From>
        <To>
          <StopPointRef>6490IM185</StopPointRef>
        </To>
        <Direction>inbound</Direction>
      </RouteLink>
      <RouteLink id="AGAK020_001_30525">
        <From>
          <StopPointRef>6490IM185</StopPointRef>
        </From>
        <To>
          <StopPointRef>6490IM1832</StopPointRef>
        </To>
        <Direction>inbound</Direction>
      </RouteLink>
      <RouteLink id="AGAK020_001_30526">
        <From>
          <StopPointRef>6490IM1832</StopPointRef>
        </From>
        <To>
          <StopPointRef>6490IM1827</StopPointRef>
        </To>
        <Direction>inbound</Direction>
      </RouteLink>
      <RouteLink id="AGAK020_001_30527">
        <From>
          <StopPointRef>6490IM1827</StopPointRef>
        </From>
        <To>
          <StopPointRef>6490IM1829</StopPointRef>
        </To>
        <Direction>inbound</Direction>
      </RouteLink>
      <RouteLink id="AGAK020_001_30528">
        <From>
          <StopPointRef>6490IM1829</StopPointRef>
        </From>
        <To>
          <StopPointRef>6490IM068</StopPointRef>
        </To>
        <Direction>inbound</Direction>
      </RouteLink>
      <RouteLink id="AGAK020_001_30529">
        <From>
          <StopPointRef>6490IM068</StopPointRef>
        </From>
        <To>
          <StopPointRef>6490IM989</StopPointRef>
        </To>
        <Direction>inbound</Direction>
      </RouteLink>
      <RouteLink id="AGAK020_001_30530">
        <From>
          <StopPointRef>6490IM989</StopPointRef>
        </From>
        <To>
          <StopPointRef>6490IM18889</StopPointRef>
        </To>
        <Direction>inbound</Direction>
      </RouteLink>
      <RouteLink id="AGAK020_001_30531">
        <From>
          <StopPointRef>6490IM18889</StopPointRef>
        </From>
        <To>
          <StopPointRef>6490IM987</StopPointRef>
        </To>
        <Direction>inbound</Direction>
      </RouteLink>
      <RouteLink id="AGAK020_001_30532">
        <From>
          <StopPointRef>6490IM987</StopPointRef>
        </From>
        <To>
          <StopPointRef>6490IM763</StopPointRef>
        </To>
        <Direction>inbound</Direction>
      </RouteLink>
      <RouteLink id="AGAK020_001_30533">
        <From>
          <StopPointRef>6490IM763</StopPointRef>
        </From>
        <To>
          <StopPointRef>6490IM642</StopPointRef>
        </To>
        <Direction>inbound</Direction>
      </RouteLink>
      <RouteLink id="AGAK020_001_30534">
        <From>
          <StopPointRef>6490IM642</StopPointRef>
        </From>
        <To>
          <StopPointRef>6490IM918</StopPointRef>
        </To>
        <Direction>inbound</Direction>
      </RouteLink>
      <RouteLink id="AGAK020_001_30535">
        <From>
          <StopPointRef>6490IM918</StopPointRef>
        </From>
        <To>
          <StopPointRef>6490IM643</StopPointRef>
        </To>
        <Direction>inbound</Direction>
      </RouteLink>
      <RouteLink id="AGAK020_001_30536">
        <From>
          <StopPointRef>6490IM643</StopPointRef>
        </From>
        <To>
          <StopPointRef>6490IM766</StopPointRef>
        </To>
        <Direction>inbound</Direction>
      </RouteLink>
      <RouteLink id="AGAK020_001_30537">
        <From>
          <StopPointRef>6490IM766</StopPointRef>
        </From>
        <To>
          <StopPointRef>6490IM481</StopPointRef>
        </To>
        <Direction>inbound</Direction>
      </RouteLink>
      <RouteLink id="AGAK020_001_30538">
        <From>
          <StopPointRef>6490IM481</StopPointRef>
        </From>
        <To>
          <StopPointRef>6490IM271</StopPointRef>
        </To>
        <Direction>inbound</Direction>
      </RouteLink>
      <RouteLink id="AGAK020_001_30539">
        <From>
          <StopPointRef>6490IM271</StopPointRef>
        </From>
        <To>
          <StopPointRef>6490IM1008</StopPointRef>
        </To>
        <Direction>inbound</Direction>
      </RouteLink>
      <RouteLink id="AGAK020_001_30540">
        <From>
          <StopPointRef>6490IM1008</StopPointRef>
        </From>
        <To>
          <StopPointRef>6490IM450</StopPointRef>
        </To>
        <Direction>inbound</Direction>
      </RouteLink>
      <RouteLink id="AGAK020_001_30541">
        <From>
          <StopPointRef>6490IM450</StopPointRef>
        </From>
        <To>
          <StopPointRef>6490IM901</StopPointRef>
        </To>
        <Direction>inbound</Direction>
      </RouteLink>
    </RouteSection>
    <RouteSection id="AGAK020_002">
      <RouteLink id="AGAK020_002_30543">
        <From>
          <StopPointRef>6490IM918</StopPointRef>
        </From>
        <To>
          <StopPointRef>6490IM643</StopPointRef>
        </To>
        <Direction>inbound</Direction>
      </RouteLink>
      <RouteLink id="AGAK020_002_30544">
        <From>
          <StopPointRef>6490IM643</StopPointRef>
        </From>
        <To>
          <StopPointRef>6490IM766</StopPointRef>
        </To>
        <Direction>inbound</Direction>
      </RouteLink>
      <RouteLink id="AGAK020_002_30545">
        <From>
          <StopPointRef>6490IM766</StopPointRef>
        </From>
        <To>
          <StopPointRef>6490IM481</StopPointRef>
        </To>
        <Direction>inbound</Direction>
      </RouteLink>
      <RouteLink id="AGAK020_002_30546">
        <From>
          <StopPointRef>6490IM481</StopPointRef>
        </From>
        <To>
          <StopPointRef>6490IM271</StopPointRef>
        </To>
        <Direction>inbound</Direction>
      </RouteLink>
      <RouteLink id="AGAK020_002_30547">
        <From>
          <StopPointRef>6490IM271</StopPointRef>
        </From>
        <To>
          <StopPointRef>6490IM1008</StopPointRef>
        </To>
        <Direction>inbound</Direction>
      </RouteLink>
      <RouteLink id="AGAK020_002_30548">
        <From>
          <StopPointRef>6490IM1008</StopPointRef>
        </From>
        <To>
          <StopPointRef>6490IM450</StopPointRef>
        </To>
        <Direction>inbound</Direction>
      </RouteLink>
      <RouteLink id="AGAK020_002_30549">
        <From>
          <StopPointRef>6490IM450</StopPointRef>
        </From>
        <To>
          <StopPointRef>6490IM901</StopPointRef>
        </To>
        <Direction>inbound</Direction>
      </RouteLink>
      <RouteLink id="AGAK020_002_30550">
        <From>
          <StopPointRef>6490IM901</StopPointRef>
        </From>
        <To>
          <StopPointRef>6490IM1009</StopPointRef>
        </To>
        <Direction>inbound</Direction>
      </RouteLink>
      <RouteLink id="AGAK020_002_30551">
        <From>
          <StopPointRef>6490IM1009</StopPointRef>
        </From>
        <To>
          <StopPointRef>6490IM55</StopPointRef>
        </To>
        <Direction>inbound</Direction>
      </RouteLink>
      <RouteLink id="AGAK020_002_30552">
        <From>
          <StopPointRef>6490IM55</StopPointRef>
        </From>
        <To>
          <StopPointRef>6490IM481</StopPointRef>
        </To>
        <Direction>inbound</Direction>
      </RouteLink>
      <RouteLink id="AGAK020_002_30553">
        <From>
          <StopPointRef>6490IM481</StopPointRef>
        </From>
        <To>
          <StopPointRef>6490IM1021</StopPointRef>
        </To>
        <Direction>inbound</Direction>
      </RouteLink>
      <RouteLink id="AGAK020_002_30554">
        <From>
          <StopPointRef>6490IM1021</StopPointRef>
        </From>
        <To>
          <StopPointRef>6490IM1955</StopPointRef>
        </To>
        <Direction>inbound</Direction>
      </RouteLink>
      <RouteLink id="AGAK020_002_30555">
        <From>
          <StopPointRef>6490IM1955</StopPointRef>
        </From>
        <To>
          <StopPointRef>6490IM1880</StopPointRef>
        </To>
        <Direction>inbound</Direction>
      </RouteLink>
      <RouteLink id="AGAK020_002_30556">
        <From>
          <StopPointRef>6490IM1880</StopPointRef>
        </From>
        <To>
          <StopPointRef>6490IM009</StopPointRef>
        </To>
        <Direction>inbound</Direction>
      </RouteLink>
      <RouteLink id="AGAK020_002_30557">
        <From>
          <StopPointRef>6490IM009</StopPointRef>
        </From>
        <To>
          <StopPointRef>6490IM1886</StopPointRef>
        </To>
        <Direction>inbound</Direction>
      </RouteLink>
      <RouteLink id="AGAK020_002_30558">
        <From>
          <StopPointRef>6490IM1886</StopPointRef>
        </From>
        <To>
          <StopPointRef>6490IM1716</StopPointRef>
        </To>
        <Direction>inbound</Direction>
      </RouteLink>
      <RouteLink id="AGAK020_002_30559">
        <From>
          <StopPointRef>6490IM1716</StopPointRef>
        </From>
        <To>
          <StopPointRef>6490IM018</StopPointRef>
        </To>
        <Direction>inbound</Direction>
      </RouteLink>
      <RouteLink id="AGAK020_002_30560">
        <From>
          <StopPointRef>6490IM018</StopPointRef>
        </From>
        <To>
          <StopPointRef>6490IM920</StopPointRef>
        </To>
        <Direction>inbound</Direction>
      </RouteLink>
      <RouteLink id="AGAK020_002_30561">
        <From>
          <StopPointRef>6490IM920</StopPointRef>
        </From>
        <To>
          <StopPointRef>6490IM185</StopPointRef>
        </To>
        <Direction>inbound</Direction>
      </RouteLink>
      <RouteLink id="AGAK020_002_30562">
        <From>
          <StopPointRef>6490IM185</StopPointRef>
        </From>
        <To>
          <StopPointRef>6490IM1832</StopPointRef>
        </To>
        <Direction>inbound</Direction>
      </RouteLink>
      <RouteLink id="AGAK020_002_30563">
        <From>
          <StopPointRef>6490IM1832</StopPointRef>
        </From>
        <To>
          <StopPointRef>6490IM1827</StopPointRef>
        </To>
        <Direction>inbound</Direction>
      </RouteLink>
      <RouteLink id="AGAK020_002_30564">
        <From>
          <StopPointRef>6490IM1827</StopPointRef>
        </From>
        <To>
          <StopPointRef>6490IM1829</StopPointRef>
        </To>
        <Direction>inbound</Direction>
      </RouteLink>
      <RouteLink id="AGAK020_002_30565">
        <From>
          <StopPointRef>6490IM1829</StopPointRef>
        </From>
        <To>
          <StopPointRef>6490IM068</StopPointRef>
        </To>
        <Direction>inbound</Direction>
      </RouteLink>
      <RouteLink id="AGAK020_002_30566">
        <From>
          <StopPointRef>6490IM068</StopPointRef>
        </From>
        <To>
          <StopPointRef>6490IM989</StopPointRef>
        </To>
        <Direction>inbound</Direction>
      </RouteLink>
      <RouteLink id="AGAK020_002_30567">
        <From>
          <StopPointRef>6490IM989</StopPointRef>
        </From>
        <To>
          <StopPointRef>6490IM18889</StopPointRef>
        </To>
        <Direction>inbound</Direction>
      </RouteLink>
    </RouteSection>
    <RouteSection id="AGAK020_003">
      <RouteLink id="AGAK020_003_30569">
        <From>
          <StopPointRef>6490IM901</StopPointRef>
        </From>
        <To>
          <StopPointRef>6490IM1009</StopPointRef>
        </To>
        <Direction>outbound</Direction>
      </RouteLink>
      <RouteLink id="AGAK020_003_30570">
        <From>
          <StopPointRef>6490IM1009</StopPointRef>
        </From>
        <To>
          <StopPointRef>6490IM55</StopPointRef>
        </To>
        <Direction>outbound</Direction>
      </RouteLink>
      <RouteLink id="AGAK020_003_30571">
        <From>
          <StopPointRef>6490IM55</StopPointRef>
        </From>
        <To>
          <StopPointRef>6490IM481</StopPointRef>
        </To>
        <Direction>outbound</Direction>
      </RouteLink>
      <RouteLink id="AGAK020_003_30572">
        <From>
          <StopPointRef>6490IM481</StopPointRef>
        </From>
        <To>
          <StopPointRef>6490IM1021</StopPointRef>
        </To>
        <Direction>outbound</Direction>
      </RouteLink>
      <RouteLink id="AGAK020_003_30573">
        <From>
          <StopPointRef>6490IM1021</StopPointRef>
        </From>
        <To>
          <StopPointRef>6490IM1955</StopPointRef>
        </To>
        <Direction>outbound</Direction>
      </RouteLink>
      <RouteLink id="AGAK020_003_30574">
        <From>
          <StopPointRef>6490IM1955</StopPointRef>
        </From>
        <To>
          <StopPointRef>6490IM1880</StopPointRef>
        </To>
        <Direction>outbound</Direction>
      </RouteLink>
      <RouteLink id="AGAK020_003_30575">
        <From>
          <StopPointRef>6490IM1880</StopPointRef>
        </From>
        <To>
          <StopPointRef>6490IM009</StopPointRef>
        </To>
        <Direction>outbound</Direction>
      </RouteLink>
      <RouteLink id="AGAK020_003_30576">
        <From>
          <StopPointRef>6490IM009</StopPointRef>
        </From>
        <To>
          <StopPointRef>6490IM1886</StopPointRef>
        </To>
        <Direction>outbound</Direction>
      </RouteLink>
      <RouteLink id="AGAK020_003_30577">
        <From>
          <StopPointRef>6490IM1886</StopPointRef>
        </From>
        <To>
          <StopPointRef>6490IM1716</StopPointRef>
        </To>
        <Direction>outbound</Direction>
      </RouteLink>
      <RouteLink id="AGAK020_003_30578">
        <From>
          <StopPointRef>6490IM1716</StopPointRef>
        </From>
        <To>
          <StopPointRef>6490IM018</StopPointRef>
        </To>
        <Direction>outbound</Direction>
      </RouteLink>
      <RouteLink id="AGAK020_003_30579">
        <From>
          <StopPointRef>6490IM018</StopPointRef>
        </From>
        <To>
          <StopPointRef>6490IM920</StopPointRef>
        </To>
        <Direction>outbound</Direction>
      </RouteLink>
      <RouteLink id="AGAK020_003_30580">
        <From>
          <StopPointRef>6490IM920</StopPointRef>
        </From>
        <To>
          <StopPointRef>6490IM185</StopPointRef>
        </To>
        <Direction>outbound</Direction>
      </RouteLink>
      <RouteLink id="AGAK020_003_30581">
        <From>
          <StopPointRef>6490IM185</StopPointRef>
        </From>
        <To>
          <StopPointRef>6490IM1832</StopPointRef>
        </To>
        <Direction>outbound</Direction>
      </RouteLink>
      <RouteLink id="AGAK020_003_30582">
        <From>
          <StopPointRef>6490IM1832</StopPointRef>
        </From>
        <To>
          <StopPointRef>6490IM1827</StopPointRef>
        </To>
        <Direction>outbound</Direction>
      </RouteLink>
      <RouteLink id="AGAK020_003_30583">
        <From>
          <StopPointRef>6490IM1827</StopPointRef>
        </From>
        <To>
          <StopPointRef>6490IM1829</StopPointRef>
        </To>
        <Direction>outbound</Direction>
      </RouteLink>
      <RouteLink id="AGAK020_003_30584">
        <From>
          <StopPointRef>6490IM1829</StopPointRef>
        </From>
        <To>
          <StopPointRef>6490IM068</StopPointRef>
        </To>
        <Direction>outbound</Direction>
      </RouteLink>
      <RouteLink id="AGAK020_003_30585">
        <From>
          <StopPointRef>6490IM068</StopPointRef>
        </From>
        <To>
          <StopPointRef>6490IM989</StopPointRef>
        </To>
        <Direction>outbound</Direction>
      </RouteLink>
      <RouteLink id="AGAK020_003_30586">
        <From>
          <StopPointRef>6490IM989</StopPointRef>
        </From>
        <To>
          <StopPointRef>6490IM18889</StopPointRef>
        </To>
        <Direction>outbound</Direction>
      </RouteLink>
    </RouteSection>
  </RouteSections>
  <Routes>
    <Route id="AGAK020_001">
      <Description>Justinhaugh and Shielhill - Kirriemuir Schools
</Description>
      <RouteSectionRef>AGAK020_001</RouteSectionRef>
    </Route>
    <Route id="AGAK020_002">
      <Description>Justinhaugh and Shielhill - Kirriemuir Schools
</Description>
      <RouteSectionRef>AGAK020_002</RouteSectionRef>
    </Route>
    <Route id="AGAK020_003">
      <Description>Route description unavailable
</Description>
      <RouteSectionRef>AGAK020_003</RouteSectionRef>
    </Route>
  </Routes>
  <JourneyPatternSections>
    <JourneyPatternSection id="JPS_AGAK020-4">
      <JourneyPatternTimingLink id="JPS_AGAK020-4_30519">
        <From>
          <StopPointRef>6490IM1880</StopPointRef>
          <TimingStatus>PTP</TimingStatus>
        </From>
        <To>
          <StopPointRef>6490IM009</StopPointRef>
          <TimingStatus>PTP</TimingStatus>
        </To>
        <RouteLinkRef>AGAK020_001_30519</RouteLinkRef>
        <Direction>inbound</Direction>
        <RunTime>PT120S</RunTime>
      </JourneyPatternTimingLink>
      <JourneyPatternTimingLink id="JPS_AGAK020-4_30520">
        <From>
          <StopPointRef>6490IM009</StopPointRef>
          <TimingStatus>PTP</TimingStatus>
        </From>
        <To>
          <StopPointRef>6490IM1886</StopPointRef>
          <TimingStatus>PTP</TimingStatus>
        </To>
        <RouteLinkRef>AGAK020_001_30520</RouteLinkRef>
        <Direction>inbound</Direction>
        <RunTime>PT420S</RunTime>
      </JourneyPatternTimingLink>
      <JourneyPatternTimingLink id="JPS_AGAK020-4_30521">
        <From>
          <StopPointRef>6490IM1886</StopPointRef>
          <TimingStatus>PTP</TimingStatus>
        </From>
        <To>
          <StopPointRef>6490IM1716</StopPointRef>
          <TimingStatus>OTH</TimingStatus>
        </To>
        <RouteLinkRef>AGAK020_001_30521</RouteLinkRef>
        <Direction>inbound</Direction>
        <RunTime>PT60S</RunTime>
      </JourneyPatternTimingLink>
      <JourneyPatternTimingLink id="JPS_AGAK020-4_30522">
        <From>
          <StopPointRef>6490IM1716</StopPointRef>
          <TimingStatus>OTH</TimingStatus>
        </From>
        <To>
          <StopPointRef>6490IM018</StopPointRef>
          <TimingStatus>OTH</TimingStatus>
        </To>
        <RouteLinkRef>AGAK020_001_30522</RouteLinkRef>
        <Direction>inbound</Direction>
        <RunTime>PT120S</RunTime>
      </JourneyPatternTimingLink>
      <JourneyPatternTimingLink id="JPS_AGAK020-4_30523">
        <From>
          <StopPointRef>6490IM018</StopPointRef>
          <TimingStatus>OTH</TimingStatus>
        </From>
        <To>
          <StopPointRef>6490IM920</StopPointRef>
          <TimingStatus>PTP</TimingStatus>
        </To>
        <RouteLinkRef>AGAK020_001_30523</RouteLinkRef>
        <Direction>inbound</Direction>
        <RunTime>PT60S</RunTime>
      </JourneyPatternTimingLink>
      <JourneyPatternTimingLink id="JPS_AGAK020-4_30524">
        <From>
          <StopPointRef>6490IM920</StopPointRef>
          <TimingStatus>PTP</TimingStatus>
        </From>
        <To>
          <StopPointRef>6490IM185</StopPointRef>
          <TimingStatus>PTP</TimingStatus>
        </To>
        <RouteLinkRef>AGAK020_001_30524</RouteLinkRef>
        <Direction>inbound</Direction>
        <RunTime>PT120S</RunTime>
      </JourneyPatternTimingLink>
      <JourneyPatternTimingLink id="JPS_AGAK020-4_30525">
        <From>
          <StopPointRef>6490IM185</StopPointRef>
          <TimingStatus>PTP</TimingStatus>
        </From>
        <To>
          <StopPointRef>6490IM1832</StopPointRef>
          <TimingStatus>OTH</TimingStatus>
        </To>
        <RouteLinkRef>AGAK020_001_30525</RouteLinkRef>
        <Direction>inbound</Direction>
        <RunTime>PT180S</RunTime>
      </JourneyPatternTimingLink>
      <JourneyPatternTimingLink id="JPS_AGAK020-4_30526">
        <From>
          <StopPointRef>6490IM1832</StopPointRef>
          <TimingStatus>OTH</TimingStatus>
        </From>
        <To>
          <StopPointRef>6490IM1827</StopPointRef>
          <TimingStatus>OTH</TimingStatus>
        </To>
        <RouteLinkRef>AGAK020_001_30526</RouteLinkRef>
        <Direction>inbound</Direction>
        <RunTime>PT0S</RunTime>
      </JourneyPatternTimingLink>
      <JourneyPatternTimingLink id="JPS_AGAK020-4_30527">
        <From>
          <StopPointRef>6490IM1827</StopPointRef>
          <TimingStatus>OTH</TimingStatus>
        </From>
        <To>
          <StopPointRef>6490IM1829</StopPointRef>
          <TimingStatus>OTH</TimingStatus>
        </To>
        <RouteLinkRef>AGAK020_001_30527</RouteLinkRef>
        <Direction>inbound</Direction>
        <RunTime>PT120S</RunTime>
      </JourneyPatternTimingLink>
      <JourneyPatternTimingLink id="JPS_AGAK020-4_30528">
        <From>
          <StopPointRef>6490IM1829</StopPointRef>
          <TimingStatus>OTH</TimingStatus>
        </From>
        <To>
          <StopPointRef>6490IM068</StopPointRef>
          <TimingStatus>PTP</TimingStatus>
        </To>
        <RouteLinkRef>AGAK020_001_30528</RouteLinkRef>
        <Direction>inbound</Direction>
        <RunTime>PT60S</RunTime>
      </JourneyPatternTimingLink>
      <JourneyPatternTimingLink id="JPS_AGAK020-4_30529">
        <From>
          <StopPointRef>6490IM068</StopPointRef>
          <TimingStatus>PTP</TimingStatus>
        </From>
        <To>
          <StopPointRef>6490IM989</StopPointRef>
          <TimingStatus>PTP</TimingStatus>
        </To>
        <RouteLinkRef>AGAK020_001_30529</RouteLinkRef>
        <Direction>inbound</Direction>
        <RunTime>PT240S</RunTime>
      </JourneyPatternTimingLink>
      <JourneyPatternTimingLink id="JPS_AGAK020-4_30530">
        <From>
          <StopPointRef>6490IM989</StopPointRef>
          <TimingStatus>PTP</TimingStatus>
        </From>
        <To>
          <StopPointRef>6490IM18889</StopPointRef>
          <TimingStatus>PTP</TimingStatus>
        </To>
        <RouteLinkRef>AGAK020_001_30530</RouteLinkRef>
        <Direction>inbound</Direction>
        <RunTime>PT240S</RunTime>
      </JourneyPatternTimingLink>
      <JourneyPatternTimingLink id="JPS_AGAK020-4_30531">
        <From>
          <StopPointRef>6490IM18889</StopPointRef>
          <TimingStatus>PTP</TimingStatus>
        </From>
        <To>
          <StopPointRef>6490IM987</StopPointRef>
          <TimingStatus>OTH</TimingStatus>
        </To>
        <RouteLinkRef>AGAK020_001_30531</RouteLinkRef>
        <Direction>inbound</Direction>
        <RunTime>PT420S</RunTime>
      </JourneyPatternTimingLink>
      <JourneyPatternTimingLink id="JPS_AGAK020-4_30532">
        <From>
          <StopPointRef>6490IM987</StopPointRef>
          <TimingStatus>OTH</TimingStatus>
        </From>
        <To>
          <StopPointRef>6490IM763</StopPointRef>
          <TimingStatus>OTH</TimingStatus>
        </To>
        <RouteLinkRef>AGAK020_001_30532</RouteLinkRef>
        <Direction>inbound</Direction>
        <RunTime>PT60S</RunTime>
      </JourneyPatternTimingLink>
      <JourneyPatternTimingLink id="JPS_AGAK020-4_30533">
        <From>
          <StopPointRef>6490IM763</StopPointRef>
          <TimingStatus>OTH</TimingStatus>
        </From>
        <To>
          <StopPointRef>6490IM642</StopPointRef>
          <TimingStatus>OTH</TimingStatus>
        </To>
        <RouteLinkRef>AGAK020_001_30533</RouteLinkRef>
        <Direction>inbound</Direction>
        <RunTime>PT60S</RunTime>
      </JourneyPatternTimingLink>
      <JourneyPatternTimingLink id="JPS_AGAK020-4_30534">
        <From>
          <StopPointRef>6490IM642</StopPointRef>
          <TimingStatus>OTH</TimingStatus>
        </From>
        <To>
          <StopPointRef>6490IM918</StopPointRef>
          <TimingStatus>PTP</TimingStatus>
        </To>
        <RouteLinkRef>AGAK020_001_30534</RouteLinkRef>
        <Direction>inbound</Direction>
        <RunTime>PT60S</RunTime>
      </JourneyPatternTimingLink>
      <JourneyPatternTimingLink id="JPS_AGAK020-4_30535">
        <From>
          <StopPointRef>6490IM918</StopPointRef>
          <TimingStatus>PTP</TimingStatus>
        </From>
        <To>
          <StopPointRef>6490IM643</StopPointRef>
          <TimingStatus>OTH</TimingStatus>
        </To>
        <RouteLinkRef>AGAK020_001_30535</RouteLinkRef>
        <Direction>inbound</Direction>
        <RunTime>PT0S</RunTime>
      </JourneyPatternTimingLink>
      <JourneyPatternTimingLink id="JPS_AGAK020-4_30536">
        <From>
          <StopPointRef>6490IM643</StopPointRef>
          <TimingStatus>OTH</TimingStatus>
        </From>
        <To>
          <StopPointRef>6490IM766</StopPointRef>
          <TimingStatus>OTH</TimingStatus>
        </To>
        <RouteLinkRef>AGAK020_001_30536</RouteLinkRef>
        <Direction>inbound</Direction>
        <RunTime>PT60S</RunTime>
      </JourneyPatternTimingLink>
      <JourneyPatternTimingLink id="JPS_AGAK020-4_30537">
        <From>
          <StopPointRef>6490IM766</StopPointRef>
          <TimingStatus>OTH</TimingStatus>
        </From>
        <To>
          <StopPointRef>6490IM481</StopPointRef>
          <TimingStatus>OTH</TimingStatus>
        </To>
        <RouteLinkRef>AGAK020_001_30537</RouteLinkRef>
        <Direction>inbound</Direction>
        <RunTime>PT60S</RunTime>
      </JourneyPatternTimingLink>
      <JourneyPatternTimingLink id="JPS_AGAK020-4_30538">
        <From>
          <StopPointRef>6490IM481</StopPointRef>
          <TimingStatus>OTH</TimingStatus>
        </From>
        <To>
          <StopPointRef>6490IM271</StopPointRef>
          <TimingStatus>OTH</TimingStatus>
        </To>
        <RouteLinkRef>AGAK020_001_30538</RouteLinkRef>
        <Direction>inbound</Direction>
        <RunTime>PT60S</RunTime>
      </JourneyPatternTimingLink>
      <JourneyPatternTimingLink id="JPS_AGAK020-4_30539">
        <From>
          <StopPointRef>6490IM271</StopPointRef>
          <TimingStatus>OTH</TimingStatus>
        </From>
        <To>
          <StopPointRef>6490IM1008</StopPointRef>
          <TimingStatus>OTH</TimingStatus>
        </To>
        <RouteLinkRef>AGAK020_001_30539</RouteLinkRef>
        <Direction>inbound</Direction>
        <RunTime>PT60S</RunTime>
      </JourneyPatternTimingLink>
      <JourneyPatternTimingLink id="JPS_AGAK020-4_30540">
        <From>
          <StopPointRef>6490IM1008</StopPointRef>
          <TimingStatus>OTH</TimingStatus>
        </From>
        <To>
          <StopPointRef>6490IM450</StopPointRef>
          <TimingStatus>OTH</TimingStatus>
        </To>
        <RouteLinkRef>AGAK020_001_30540</RouteLinkRef>
        <Direction>inbound</Direction>
        <RunTime>PT0S</RunTime>
      </JourneyPatternTimingLink>
      <JourneyPatternTimingLink id="JPS_AGAK020-4_30541">
        <From>
          <StopPointRef>6490IM450</StopPointRef>
          <TimingStatus>OTH</TimingStatus>
        </From>
        <To>
          <StopPointRef>6490IM901</StopPointRef>
          <TimingStatus>PTP</TimingStatus>
        </To>
        <RouteLinkRef>AGAK020_001_30541</RouteLinkRef>
        <Direction>inbound</Direction>
        <RunTime>PT60S</RunTime>
      </JourneyPatternTimingLink>
    </JourneyPatternSection>
    <JourneyPatternSection id="JPS_AGAK020-5">
      <JourneyPatternTimingLink id="JPS_AGAK020-5_30543">
        <From>
          <StopPointRef>6490IM918</StopPointRef>
          <TimingStatus>PTP</TimingStatus>
        </From>
        <To>
          <StopPointRef>6490IM643</StopPointRef>
          <TimingStatus>OTH</TimingStatus>
        </To>
        <RouteLinkRef>AGAK020_002_30543</RouteLinkRef>
        <Direction>inbound</Direction>
        <RunTime>PT60S</RunTime>
      </JourneyPatternTimingLink>
      <JourneyPatternTimingLink id="JPS_AGAK020-5_30544">
        <From>
          <StopPointRef>6490IM643</StopPointRef>
          <TimingStatus>OTH</TimingStatus>
        </From>
        <To>
          <StopPointRef>6490IM766</StopPointRef>
          <TimingStatus>OTH</TimingStatus>
        </To>
        <RouteLinkRef>AGAK020_002_30544</RouteLinkRef>
        <Direction>inbound</Direction>
        <RunTime>PT0S</RunTime>
      </JourneyPatternTimingLink>
      <JourneyPatternTimingLink id="JPS_AGAK020-5_30545">
        <From>
          <StopPointRef>6490IM766</StopPointRef>
          <TimingStatus>OTH</TimingStatus>
        </From>
        <To>
          <StopPointRef>6490IM481</StopPointRef>
          <TimingStatus>OTH</TimingStatus>
        </To>
        <RouteLinkRef>AGAK020_002_30545</RouteLinkRef>
        <Direction>inbound</Direction>
        <RunTime>PT60S</RunTime>
      </JourneyPatternTimingLink>
      <JourneyPatternTimingLink id="JPS_AGAK020-5_30546">
        <From>
          <StopPointRef>6490IM481</StopPointRef>
          <TimingStatus>OTH</TimingStatus>
        </From>
        <To>
          <StopPointRef>6490IM271</StopPointRef>
          <TimingStatus>OTH</TimingStatus>
        </To>
        <RouteLinkRef>AGAK020_002_30546</RouteLinkRef>
        <Direction>inbound</Direction>
        <RunTime>PT60S</RunTime>
      </JourneyPatternTimingLink>
      <JourneyPatternTimingLink id="JPS_AGAK020-5_30547">
        <From>
          <StopPointRef>6490IM271</StopPointRef>
          <TimingStatus>OTH</TimingStatus>
        </From>
        <To>
          <StopPointRef>6490IM1008</StopPointRef>
          <TimingStatus>OTH</TimingStatus>
        </To>
        <RouteLinkRef>AGAK020_002_30547</RouteLinkRef>
        <Direction>inbound</Direction>
        <RunTime>PT60S</RunTime>
      </JourneyPatternTimingLink>
      <JourneyPatternTimingLink id="JPS_AGAK020-5_30548">
        <From>
          <StopPointRef>6490IM1008</StopPointRef>
          <TimingStatus>OTH</TimingStatus>
        </From>
        <To>
          <StopPointRef>6490IM450</StopPointRef>
          <TimingStatus>OTH</TimingStatus>
        </To>
        <RouteLinkRef>AGAK020_002_30548</RouteLinkRef>
        <Direction>inbound</Direction>
        <RunTime>PT60S</RunTime>
      </JourneyPatternTimingLink>
      <JourneyPatternTimingLink id="JPS_AGAK020-5_30549">
        <From>
          <StopPointRef>6490IM450</StopPointRef>
          <TimingStatus>OTH</TimingStatus>
        </From>
        <To>
          <StopPointRef>6490IM901</StopPointRef>
          <TimingStatus>PTP</TimingStatus>
        </To>
        <RouteLinkRef>AGAK020_002_30549</RouteLinkRef>
        <Direction>inbound</Direction>
        <RunTime>PT60S</RunTime>
      </JourneyPatternTimingLink>
      <JourneyPatternTimingLink id="JPS_AGAK020-5_30550">
        <From>
          <WaitTime>PT1440S</WaitTime>
          <StopPointRef>6490IM901</StopPointRef>
          <TimingStatus>PTP</TimingStatus>
        </From>
        <To>
          <StopPointRef>6490IM1009</StopPointRef>
          <TimingStatus>OTH</TimingStatus>
        </To>
        <RouteLinkRef>AGAK020_002_30550</RouteLinkRef>
        <Direction>inbound</Direction>
        <RunTime>PT60S</RunTime>
      </JourneyPatternTimingLink>
      <JourneyPatternTimingLink id="JPS_AGAK020-5_30551">
        <From>
          <StopPointRef>6490IM1009</StopPointRef>
          <TimingStatus>OTH</TimingStatus>
        </From>
        <To>
          <StopPointRef>6490IM55</StopPointRef>
          <TimingStatus>OTH</TimingStatus>
        </To>
        <RouteLinkRef>AGAK020_002_30551</RouteLinkRef>
        <Direction>inbound</Direction>
        <RunTime>PT120S</RunTime>
      </JourneyPatternTimingLink>
      <JourneyPatternTimingLink id="JPS_AGAK020-5_30552">
        <From>
          <StopPointRef>6490IM55</StopPointRef>
          <TimingStatus>OTH</TimingStatus>
        </From>
        <To>
          <StopPointRef>6490IM481</StopPointRef>
          <TimingStatus>OTH</TimingStatus>
        </To>
        <RouteLinkRef>AGAK020_002_30552</RouteLinkRef>
        <Direction>inbound</Direction>
        <RunTime>PT60S</RunTime>
      </JourneyPatternTimingLink>
      <JourneyPatternTimingLink id="JPS_AGAK020-5_30553">
        <From>
          <StopPointRef>6490IM481</StopPointRef>
          <TimingStatus>OTH</TimingStatus>
        </From>
        <To>
          <StopPointRef>6490IM1021</StopPointRef>
          <TimingStatus>OTH</TimingStatus>
        </To>
        <RouteLinkRef>AGAK020_002_30553</RouteLinkRef>
        <Direction>inbound</Direction>
        <RunTime>PT120S</RunTime>
      </JourneyPatternTimingLink>
      <JourneyPatternTimingLink id="JPS_AGAK020-5_30554">
        <From>
          <StopPointRef>6490IM1021</StopPointRef>
          <TimingStatus>OTH</TimingStatus>
        </From>
        <To>
          <StopPointRef>6490IM1955</StopPointRef>
          <TimingStatus>OTH</TimingStatus>
        </To>
        <RouteLinkRef>AGAK020_002_30554</RouteLinkRef>
        <Direction>inbound</Direction>
        <RunTime>PT120S</RunTime>
      </JourneyPatternTimingLink>
      <JourneyPatternTimingLink id="JPS_AGAK020-5_30555">
        <From>
          <StopPointRef>6490IM1955</StopPointRef>
          <TimingStatus>OTH</TimingStatus>
        </From>
        <To>
          <StopPointRef>6490IM1880</StopPointRef>
          <TimingStatus>PTP</TimingStatus>
        </To>
        <RouteLinkRef>AGAK020_002_30555</RouteLinkRef>
        <Direction>inbound</Direction>
        <RunTime>PT120S</RunTime>
      </JourneyPatternTimingLink>
      <JourneyPatternTimingLink id="JPS_AGAK020-5_30556">
        <From>
          <StopPointRef>6490IM1880</StopPointRef>
          <TimingStatus>PTP</TimingStatus>
        </From>
        <To>
          <StopPointRef>6490IM009</StopPointRef>
          <TimingStatus>PTP</TimingStatus>
        </To>
        <RouteLinkRef>AGAK020_002_30556</RouteLinkRef>
        <Direction>inbound</Direction>
        <RunTime>PT180S</RunTime>
      </JourneyPatternTimingLink>
      <JourneyPatternTimingLink id="JPS_AGAK020-5_30557">
        <From>
          <StopPointRef>6490IM009</StopPointRef>
          <TimingStatus>PTP</TimingStatus>
        </From>
        <To>
          <StopPointRef>6490IM1886</StopPointRef>
          <TimingStatus>PTP</TimingStatus>
        </To>
        <RouteLinkRef>AGAK020_002_30557</RouteLinkRef>
        <Direction>inbound</Direction>
        <RunTime>PT120S</RunTime>
      </JourneyPatternTimingLink>
      <JourneyPatternTimingLink id="JPS_AGAK020-5_30558">
        <From>
          <StopPointRef>6490IM1886</StopPointRef>
          <TimingStatus>PTP</TimingStatus>
        </From>
        <To>
          <StopPointRef>6490IM1716</StopPointRef>
          <TimingStatus>OTH</TimingStatus>
        </To>
        <RouteLinkRef>AGAK020_002_30558</RouteLinkRef>
        <Direction>inbound</Direction>
        <RunTime>PT180S</RunTime>
      </JourneyPatternTimingLink>
      <JourneyPatternTimingLink id="JPS_AGAK020-5_30559">
        <From>
          <StopPointRef>6490IM1716</StopPointRef>
          <TimingStatus>OTH</TimingStatus>
        </From>
        <To>
          <StopPointRef>6490IM018</StopPointRef>
          <TimingStatus>OTH</TimingStatus>
        </To>
        <RouteLinkRef>AGAK020_002_30559</RouteLinkRef>
        <Direction>inbound</Direction>
        <RunTime>PT240S</RunTime>
      </JourneyPatternTimingLink>
      <JourneyPatternTimingLink id="JPS_AGAK020-5_30560">
        <From>
          <StopPointRef>6490IM018</StopPointRef>
          <TimingStatus>OTH</TimingStatus>
        </From>
        <To>
          <StopPointRef>6490IM920</StopPointRef>
          <TimingStatus>PTP</TimingStatus>
        </To>
        <RouteLinkRef>AGAK020_002_30560</RouteLinkRef>
        <Direction>inbound</Direction>
        <RunTime>PT60S</RunTime>
      </JourneyPatternTimingLink>
      <JourneyPatternTimingLink id="JPS_AGAK020-5_30561">
        <From>
          <StopPointRef>6490IM920</StopPointRef>
          <TimingStatus>PTP</TimingStatus>
        </From>
        <To>
          <StopPointRef>6490IM185</StopPointRef>
          <TimingStatus>PTP</TimingStatus>
        </To>
        <RouteLinkRef>AGAK020_002_30561</RouteLinkRef>
        <Direction>inbound</Direction>
        <RunTime>PT120S</RunTime>
      </JourneyPatternTimingLink>
      <JourneyPatternTimingLink id="JPS_AGAK020-5_30562">
        <From>
          <StopPointRef>6490IM185</StopPointRef>
          <TimingStatus>PTP</TimingStatus>
        </From>
        <To>
          <StopPointRef>6490IM1832</StopPointRef>
          <TimingStatus>OTH</TimingStatus>
        </To>
        <RouteLinkRef>AGAK020_002_30562</RouteLinkRef>
        <Direction>inbound</Direction>
        <RunTime>PT180S</RunTime>
      </JourneyPatternTimingLink>
      <JourneyPatternTimingLink id="JPS_AGAK020-5_30563">
        <From>
          <StopPointRef>6490IM1832</StopPointRef>
          <TimingStatus>OTH</TimingStatus>
        </From>
        <To>
          <StopPointRef>6490IM1827</StopPointRef>
          <TimingStatus>OTH</TimingStatus>
        </To>
        <RouteLinkRef>AGAK020_002_30563</RouteLinkRef>
        <Direction>inbound</Direction>
        <RunTime>PT60S</RunTime>
      </JourneyPatternTimingLink>
      <JourneyPatternTimingLink id="JPS_AGAK020-5_30564">
        <From>
          <StopPointRef>6490IM1827</StopPointRef>
          <TimingStatus>OTH</TimingStatus>
        </From>
        <To>
          <StopPointRef>6490IM1829</StopPointRef>
          <TimingStatus>OTH</TimingStatus>
        </To>
        <RouteLinkRef>AGAK020_002_30564</RouteLinkRef>
        <Direction>inbound</Direction>
        <RunTime>PT60S</RunTime>
      </JourneyPatternTimingLink>
      <JourneyPatternTimingLink id="JPS_AGAK020-5_30565">
        <From>
          <StopPointRef>6490IM1829</StopPointRef>
          <TimingStatus>OTH</TimingStatus>
        </From>
        <To>
          <StopPointRef>6490IM068</StopPointRef>
          <TimingStatus>PTP</TimingStatus>
        </To>
        <RouteLinkRef>AGAK020_002_30565</RouteLinkRef>
        <Direction>inbound</Direction>
        <RunTime>PT60S</RunTime>
      </JourneyPatternTimingLink>
      <JourneyPatternTimingLink id="JPS_AGAK020-5_30566">
        <From>
          <StopPointRef>6490IM068</StopPointRef>
          <TimingStatus>PTP</TimingStatus>
        </From>
        <To>
          <StopPointRef>6490IM989</StopPointRef>
          <TimingStatus>PTP</TimingStatus>
        </To>
        <RouteLinkRef>AGAK020_002_30566</RouteLinkRef>
        <Direction>inbound</Direction>
        <RunTime>PT240S</RunTime>
      </JourneyPatternTimingLink>
      <JourneyPatternTimingLink id="JPS_AGAK020-5_30567">
        <From>
          <StopPointRef>6490IM989</StopPointRef>
          <TimingStatus>PTP</TimingStatus>
        </From>
        <To>
          <StopPointRef>6490IM18889</StopPointRef>
          <TimingStatus>PTP</TimingStatus>
        </To>
        <RouteLinkRef>AGAK020_002_30567</RouteLinkRef>
        <Direction>inbound</Direction>
        <RunTime>PT240S</RunTime>
      </JourneyPatternTimingLink>
    </JourneyPatternSection>
    <JourneyPatternSection id="JPS_AGAK020-6">
      <JourneyPatternTimingLink id="JPS_AGAK020-6_30569">
        <From>
          <StopPointRef>6490IM901</StopPointRef>
          <TimingStatus>PTP</TimingStatus>
        </From>
        <To>
          <StopPointRef>6490IM1009</StopPointRef>
          <TimingStatus>OTH</TimingStatus>
        </To>
        <RouteLinkRef>AGAK020_003_30569</RouteLinkRef>
        <Direction>outbound</Direction>
        <RunTime>PT60S</RunTime>
      </JourneyPatternTimingLink>
      <JourneyPatternTimingLink id="JPS_AGAK020-6_30570">
        <From>
          <StopPointRef>6490IM1009</StopPointRef>
          <TimingStatus>OTH</TimingStatus>
        </From>
        <To>
          <StopPointRef>6490IM55</StopPointRef>
          <TimingStatus>OTH</TimingStatus>
        </To>
        <RouteLinkRef>AGAK020_003_30570</RouteLinkRef>
        <Direction>outbound</Direction>
        <RunTime>PT120S</RunTime>
      </JourneyPatternTimingLink>
      <JourneyPatternTimingLink id="JPS_AGAK020-6_30571">
        <From>
          <StopPointRef>6490IM55</StopPointRef>
          <TimingStatus>OTH</TimingStatus>
        </From>
        <To>
          <StopPointRef>6490IM481</StopPointRef>
          <TimingStatus>OTH</TimingStatus>
        </To>
        <RouteLinkRef>AGAK020_003_30571</RouteLinkRef>
        <Direction>outbound</Direction>
        <RunTime>PT60S</RunTime>
      </JourneyPatternTimingLink>
      <JourneyPatternTimingLink id="JPS_AGAK020-6_30572">
        <From>
          <StopPointRef>6490IM481</StopPointRef>
          <TimingStatus>OTH</TimingStatus>
        </From>
        <To>
          <StopPointRef>6490IM1021</StopPointRef>
          <TimingStatus>OTH</TimingStatus>
        </To>
        <RouteLinkRef>AGAK020_003_30572</RouteLinkRef>
        <Direction>outbound</Direction>
        <RunTime>PT120S</RunTime>
      </JourneyPatternTimingLink>
      <JourneyPatternTimingLink id="JPS_AGAK020-6_30573">
        <From>
          <StopPointRef>6490IM1021</StopPointRef>
          <TimingStatus>OTH</TimingStatus>
        </From>
        <To>
          <StopPointRef>6490IM1955</StopPointRef>
          <TimingStatus>OTH</TimingStatus>
        </To>
        <RouteLinkRef>AGAK020_003_30573</RouteLinkRef>
        <Direction>outbound</Direction>
        <RunTime>PT120S</RunTime>
      </JourneyPatternTimingLink>
      <JourneyPatternTimingLink id="JPS_AGAK020-6_30574">
        <From>
          <StopPointRef>6490IM1955</StopPointRef>
          <TimingStatus>OTH</TimingStatus>
        </From>
        <To>
          <StopPointRef>6490IM1880</StopPointRef>
          <TimingStatus>PTP</TimingStatus>
        </To>
        <RouteLinkRef>AGAK020_003_30574</RouteLinkRef>
        <Direction>outbound</Direction>
        <RunTime>PT120S</RunTime>
      </JourneyPatternTimingLink>
      <JourneyPatternTimingLink id="JPS_AGAK020-6_30575">
        <From>
          <StopPointRef>6490IM1880</StopPointRef>
          <TimingStatus>PTP</TimingStatus>
        </From>
        <To>
          <StopPointRef>6490IM009</StopPointRef>
          <TimingStatus>PTP</TimingStatus>
        </To>
        <RouteLinkRef>AGAK020_003_30575</RouteLinkRef>
        <Direction>outbound</Direction>
        <RunTime>PT180S</RunTime>
      </JourneyPatternTimingLink>
      <JourneyPatternTimingLink id="JPS_AGAK020-6_30576">
        <From>
          <StopPointRef>6490IM009</StopPointRef>
          <TimingStatus>PTP</TimingStatus>
        </From>
        <To>
          <StopPointRef>6490IM1886</StopPointRef>
          <TimingStatus>PTP</TimingStatus>
        </To>
        <RouteLinkRef>AGAK020_003_30576</RouteLinkRef>
        <Direction>outbound</Direction>
        <RunTime>PT120S</RunTime>
      </JourneyPatternTimingLink>
      <JourneyPatternTimingLink id="JPS_AGAK020-6_30577">
        <From>
          <StopPointRef>6490IM1886</StopPointRef>
          <TimingStatus>PTP</TimingStatus>
        </From>
        <To>
          <StopPointRef>6490IM1716</StopPointRef>
          <TimingStatus>OTH</TimingStatus>
        </To>
        <RouteLinkRef>AGAK020_003_30577</RouteLinkRef>
        <Direction>outbound</Direction>
        <RunTime>PT180S</RunTime>
      </JourneyPatternTimingLink>
      <JourneyPatternTimingLink id="JPS_AGAK020-6_30578">
        <From>
          <StopPointRef>6490IM1716</StopPointRef>
          <TimingStatus>OTH</TimingStatus>
        </From>
        <To>
          <StopPointRef>6490IM018</StopPointRef>
          <TimingStatus>OTH</TimingStatus>
        </To>
        <RouteLinkRef>AGAK020_003_30578</RouteLinkRef>
        <Direction>outbound</Direction>
        <RunTime>PT120S</RunTime>
      </JourneyPatternTimingLink>
      <JourneyPatternTimingLink id="JPS_AGAK020-6_30579">
        <From>
          <StopPointRef>6490IM018</StopPointRef>
          <TimingStatus>OTH</TimingStatus>
        </From>
        <To>
          <StopPointRef>6490IM920</StopPointRef>
          <TimingStatus>PTP</TimingStatus>
        </To>
        <RouteLinkRef>AGAK020_003_30579</RouteLinkRef>
        <Direction>outbound</Direction>
        <RunTime>PT60S</RunTime>
      </JourneyPatternTimingLink>
      <JourneyPatternTimingLink id="JPS_AGAK020-6_30580">
        <From>
          <StopPointRef>6490IM920</StopPointRef>
          <TimingStatus>PTP</TimingStatus>
        </From>
        <To>
          <StopPointRef>6490IM185</StopPointRef>
          <TimingStatus>PTP</TimingStatus>
        </To>
        <RouteLinkRef>AGAK020_003_30580</RouteLinkRef>
        <Direction>outbound</Direction>
        <RunTime>PT120S</RunTime>
      </JourneyPatternTimingLink>
      <JourneyPatternTimingLink id="JPS_AGAK020-6_30581">
        <From>
          <StopPointRef>6490IM185</StopPointRef>
          <TimingStatus>PTP</TimingStatus>
        </From>
        <To>
          <StopPointRef>6490IM1832</StopPointRef>
          <TimingStatus>OTH</TimingStatus>
        </To>
        <RouteLinkRef>AGAK020_003_30581</RouteLinkRef>
        <Direction>outbound</Direction>
        <RunTime>PT120S</RunTime>
      </JourneyPatternTimingLink>
      <JourneyPatternTimingLink id="JPS_AGAK020-6_30582">
        <From>
          <StopPointRef>6490IM1832</StopPointRef>
          <TimingStatus>OTH</TimingStatus>
        </From>
        <To>
          <StopPointRef>6490IM1827</StopPointRef>
          <TimingStatus>OTH</TimingStatus>
        </To>
        <RouteLinkRef>AGAK020_003_30582</RouteLinkRef>
        <Direction>outbound</Direction>
        <RunTime>PT60S</RunTime>
      </JourneyPatternTimingLink>
      <JourneyPatternTimingLink id="JPS_AGAK020-6_30583">
        <From>
          <StopPointRef>6490IM1827</StopPointRef>
          <TimingStatus>OTH</TimingStatus>
        </From>
        <To>
          <StopPointRef>6490IM1829</StopPointRef>
          <TimingStatus>OTH</TimingStatus>
        </To>
        <RouteLinkRef>AGAK020_003_30583</RouteLinkRef>
        <Direction>outbound</Direction>
        <RunTime>PT120S</RunTime>
      </JourneyPatternTimingLink>
      <JourneyPatternTimingLink id="JPS_AGAK020-6_30584">
        <From>
          <StopPointRef>6490IM1829</StopPointRef>
          <TimingStatus>OTH</TimingStatus>
        </From>
        <To>
          <StopPointRef>6490IM068</StopPointRef>
          <TimingStatus>PTP</TimingStatus>
        </To>
        <RouteLinkRef>AGAK020_003_30584</RouteLinkRef>
        <Direction>outbound</Direction>
        <RunTime>PT60S</RunTime>
      </JourneyPatternTimingLink>
      <JourneyPatternTimingLink id="JPS_AGAK020-6_30585">
        <From>
          <StopPointRef>6490IM068</StopPointRef>
          <TimingStatus>PTP</TimingStatus>
        </From>
        <To>
          <StopPointRef>6490IM989</StopPointRef>
          <TimingStatus>PTP</TimingStatus>
        </To>
        <RouteLinkRef>AGAK020_003_30585</RouteLinkRef>
        <Direction>outbound</Direction>
        <RunTime>PT180S</RunTime>
      </JourneyPatternTimingLink>
      <JourneyPatternTimingLink id="JPS_AGAK020-6_30586">
        <From>
          <StopPointRef>6490IM989</StopPointRef>
          <TimingStatus>PTP</TimingStatus>
        </From>
        <To>
          <StopPointRef>6490IM18889</StopPointRef>
          <TimingStatus>PTP</TimingStatus>
        </To>
        <RouteLinkRef>AGAK020_003_30586</RouteLinkRef>
        <Direction>outbound</Direction>
        <RunTime>PT120S</RunTime>
      </JourneyPatternTimingLink>
    </JourneyPatternSection>
  </JourneyPatternSections>
  <Operators>
    <Operator id="JPE">
      <NationalOperatorCode>JPEM</NationalOperatorCode>
      <OperatorCode>JPE</OperatorCode>
      <OperatorShortName>J P Minicoaches</OperatorShortName>
    </Operator>
  </Operators>
  <Services>
    <Service>
      <ServiceCode>AGAK020</ServiceCode>
      <Lines>
        <Line id="0">
          <LineName>K20</LineName>
        </Line>
      </Lines>
      <OperatingPeriod>
        <StartDate>2018-01-08</StartDate>
        <EndDate>2049-12-31</EndDate>
      </OperatingPeriod>
      <RegisteredOperatorRef>JPE</RegisteredOperatorRef>
      <StopRequirements>
        <NoNewStopsRequired />
      </StopRequirements>
      <Mode>bus</Mode>
      <Description>Justinhaugh and Shielhill - Kirriemuir Schools</Description>
      <StandardService>
        <Origin>Justinhaugh and Shielhill</Origin>
        <Destination>Kirriemuir Schools</Destination>
        <JourneyPattern id="JPS_AGAK020-4">
          <Direction>inbound</Direction>
          <JourneyPatternSectionRefs>JPS_AGAK020-4</JourneyPatternSectionRefs>
        </JourneyPattern>
        <JourneyPattern id="JPS_AGAK020-5">
          <Direction>inbound</Direction>
          <JourneyPatternSectionRefs>JPS_AGAK020-5</JourneyPatternSectionRefs>
        </JourneyPattern>
        <JourneyPattern id="JPS_AGAK020-6">
          <Direction>outbound</Direction>
          <JourneyPatternSectionRefs>JPS_AGAK020-6</JourneyPatternSectionRefs>
        </JourneyPattern>
      </StandardService>
    </Service>
  </Services>
  <VehicleJourneys>
    <VehicleJourney>
      <OperatorRef>JPE</OperatorRef>
      <OperatingProfile>
        <RegularDayType>
          <DaysOfWeek>
            <Monday />
            <Tuesday />
            <Wednesday />
            <Thursday />
            <Friday />
          </DaysOfWeek>
        </RegularDayType>
        <ServicedOrganisationDayType>
          <DaysOfNonOperation>
            <WorkingDays>
              <ServicedOrganisationRef>160</ServicedOrganisationRef>
            </WorkingDays>
          </DaysOfNonOperation>
        </ServicedOrganisationDayType>
      </OperatingProfile>
      <VehicleJourneyCode>12343</VehicleJourneyCode>
      <ServiceRef>AGAK020</ServiceRef>
      <LineRef>0</LineRef>
      <JourneyPatternRef>JPS_AGAK020-4</JourneyPatternRef>
      <Note>
        <NoteCode>Sch</NoteCode>
        <NoteText>Operates on Angus schooldays only</NoteText>
      </Note>
      <DepartureTime>08:01:00</DepartureTime>
    </VehicleJourney>
    <VehicleJourney>
      <OperatorRef>JPE</OperatorRef>
      <OperatingProfile>
        <RegularDayType>
          <DaysOfWeek>
            <Monday />
            <Tuesday />
            <Wednesday />
            <Thursday />
          </DaysOfWeek>
        </RegularDayType>
        <ServicedOrganisationDayType>
          <DaysOfNonOperation>
            <WorkingDays>
              <ServicedOrganisationRef>160</ServicedOrganisationRef>
            </WorkingDays>
          </DaysOfNonOperation>
        </ServicedOrganisationDayType>
      </OperatingProfile>
      <VehicleJourneyCode>12344</VehicleJourneyCode>
      <ServiceRef>AGAK020</ServiceRef>
      <LineRef>0</LineRef>
      <JourneyPatternRef>JPS_AGAK020-5</JourneyPatternRef>
      <Note>
        <NoteCode>Sch</NoteCode>
        <NoteText>Operates on Angus schooldays only</NoteText>
      </Note>
      <DepartureTime>15:30:00</DepartureTime>
    </VehicleJourney>
    <VehicleJourney>
      <OperatorRef>JPE</OperatorRef>
      <OperatingProfile>
        <RegularDayType>
          <DaysOfWeek>
            <Friday />
          </DaysOfWeek>
        </RegularDayType>
        <ServicedOrganisationDayType>
          <DaysOfNonOperation>
            <WorkingDays>
              <ServicedOrganisationRef>160</ServicedOrganisationRef>
            </WorkingDays>
          </DaysOfNonOperation>
        </ServicedOrganisationDayType>
      </OperatingProfile>
      <VehicleJourneyCode>12345</VehicleJourneyCode>
      <ServiceRef>AGAK020</ServiceRef>
      <LineRef>0</LineRef>
      <JourneyPatternRef>JPS_AGAK020-6</JourneyPatternRef>
      <Note>
        <NoteCode>Sch</NoteCode>
        <NoteText>Operates on Angus schooldays only</NoteText>
      </Note>
      <DepartureTime>13:30:00</DepartureTime>
    </VehicleJourney>
  </VehicleJourneys>
</TransXChange>