<?xml version="1.0" encoding="utf-8"?>
<TransXChange xmlns:xsi="http://www.w3.org/2001/XMLSchema-instance" xmlns:xsd="http://www.w3.org/2001/XMLSchema" xsi:schemaLocation="http://www.transxchange.org.uk/ http://www.transxchange.org.uk/schema/2.1/TransXChange_general.xsd" CreationDateTime="2019-10-07T13:20:00-00:00" ModificationDateTime="2019-10-07T13:20:00-00:00" Modification="new" RevisionNumber="0" FileName="SVRFIADF12.xml" SchemaVersion="2.1" RegistrationDocument="false" xmlns="http://www.transxchange.org.uk/">
  <ServicedOrganisations>
    <ServicedOrganisation>
      <OrganisationCode>434</OrganisationCode>
      <Name>
QE0 : Cif-FDF12-SIF-20180813_20190925_220554.cif
</Name>
      <WorkingDays>
        <DateRange>
          <StartDate>2019-09-25</StartDate>
          <EndDate>2021-01-03</EndDate>
        </DateRange>
        <DateRange>
          <StartDate>2021-01-05</StartDate>
          <EndDate>2021-12-25</EndDate>
        </DateRange>
        <DateRange>
          <StartDate>2022-01-09</StartDate>
          <EndDate>2022-12-24</EndDate>
        </DateRange>
        <DateRange>
          <StartDate>2023-01-08</StartDate>
          <EndDate>2023-12-23</EndDate>
        </DateRange>
        <DateRange>
          <StartDate>2024-01-07</StartDate>
          <EndDate>2027-01-03</EndDate>
        </DateRange>
        <DateRange>
          <StartDate>2027-01-05</StartDate>
          <EndDate>2027-12-25</EndDate>
        </DateRange>
        <DateRange>
          <StartDate>2028-01-09</StartDate>
          <EndDate>2028-08-12</EndDate>
        </DateRange>
      </WorkingDays>
    </ServicedOrganisation>
    <ServicedOrganisation>
      <OrganisationCode>435</OrganisationCode>
      <Name>
QE0 : Cif-FDF12-SIF-20180813_20190925_220554.cif
</Name>
      <WorkingDays>
        <DateRange>
          <StartDate>2019-09-25</StartDate>
          <EndDate>2028-08-12</EndDate>
        </DateRange>
      </WorkingDays>
    </ServicedOrganisation>
    <ServicedOrganisation>
      <OrganisationCode>436</OrganisationCode>
      <Name>
QE0 : Cif-FDF12-SIF-20180813_20190925_220554.cif
</Name>
      <WorkingDays>
        <DateRange>
          <StartDate>2019-09-25</StartDate>
          <EndDate>2021-01-03</EndDate>
        </DateRange>
        <DateRange>
          <StartDate>2021-01-05</StartDate>
          <EndDate>2022-01-03</EndDate>
        </DateRange>
        <DateRange>
          <StartDate>2022-01-05</StartDate>
          <EndDate>2023-01-02</EndDate>
        </DateRange>
        <DateRange>
          <StartDate>2023-01-04</StartDate>
          <EndDate>2027-01-03</EndDate>
        </DateRange>
        <DateRange>
          <StartDate>2027-01-05</StartDate>
          <EndDate>2028-01-03</EndDate>
        </DateRange>
        <DateRange>
          <StartDate>2028-01-05</StartDate>
          <EndDate>2028-08-12</EndDate>
        </DateRange>
      </WorkingDays>
    </ServicedOrganisation>
  </ServicedOrganisations>
  <StopPoints>
    <AnnotatedStopPointRef>
      <StopPointRef>6500D9357</StopPointRef>
      <CommonName>Dunfermline High School</CommonName>
    </AnnotatedStopPointRef>
    <AnnotatedStopPointRef>
      <StopPointRef>6500D9238</StopPointRef>
      <CommonName>Dunfermline High School</CommonName>
    </AnnotatedStopPointRef>
    <AnnotatedStopPointRef>
      <StopPointRef>6500D0436</StopPointRef>
      <CommonName>Dunfermline High School</CommonName>
    </AnnotatedStopPointRef>
    <AnnotatedStopPointRef>
      <StopPointRef>6500D0428</StopPointRef>
      <CommonName>Cottage Inn</CommonName>
    </AnnotatedStopPointRef>
    <AnnotatedStopPointRef>
      <StopPointRef>6500D1035</StopPointRef>
      <CommonName>King Malcolm Hotel</CommonName>
    </AnnotatedStopPointRef>
    <AnnotatedStopPointRef>
      <StopPointRef>6500D0497</StopPointRef>
      <CommonName>Cypress Grove</CommonName>
    </AnnotatedStopPointRef>
    <AnnotatedStopPointRef>
      <StopPointRef>6500D0500</StopPointRef>
      <CommonName>Pitreavie Golf Course</CommonName>
    </AnnotatedStopPointRef>
    <AnnotatedStopPointRef>
      <StopPointRef>6500D0916</StopPointRef>
      <CommonName>Pitreavie Playing Fields</CommonName>
    </AnnotatedStopPointRef>
    <AnnotatedStopPointRef>
      <StopPointRef>6500D0501</StopPointRef>
      <CommonName>Pitreavie Business Park</CommonName>
    </AnnotatedStopPointRef>
    <AnnotatedStopPointRef>
      <StopPointRef>6500D0243</StopPointRef>
      <CommonName>Carnegie Campus</CommonName>
    </AnnotatedStopPointRef>
    <AnnotatedStopPointRef>
      <StopPointRef>6500D0244</StopPointRef>
      <CommonName>Railway Station</CommonName>
    </AnnotatedStopPointRef>
    <AnnotatedStopPointRef>
      <StopPointRef>6500D0774</StopPointRef>
      <CommonName>Albert Street</CommonName>
    </AnnotatedStopPointRef>
    <AnnotatedStopPointRef>
      <StopPointRef>6500D1100</StopPointRef>
      <CommonName>King's Road Primary School</CommonName>
    </AnnotatedStopPointRef>
    <AnnotatedStopPointRef>
      <StopPointRef>6500D9180</StopPointRef>
      <CommonName>Pattiesmuir Road End</CommonName>
    </AnnotatedStopPointRef>
    <AnnotatedStopPointRef>
      <StopPointRef>6500D9165</StopPointRef>
      <CommonName>Road End</CommonName>
    </AnnotatedStopPointRef>
    <AnnotatedStopPointRef>
      <StopPointRef>6500D9182</StopPointRef>
      <CommonName>East Lodge</CommonName>
    </AnnotatedStopPointRef>
    <AnnotatedStopPointRef>
      <StopPointRef>6500D9185</StopPointRef>
      <CommonName>Waulkmill Farm</CommonName>
    </AnnotatedStopPointRef>
    <AnnotatedStopPointRef>
      <StopPointRef>6500D0594</StopPointRef>
      <CommonName>Ordnance Road</CommonName>
    </AnnotatedStopPointRef>
    <AnnotatedStopPointRef>
      <StopPointRef>6500D1110</StopPointRef>
      <CommonName>Primary School</CommonName>
    </AnnotatedStopPointRef>
    <AnnotatedStopPointRef>
      <StopPointRef>6500D1105</StopPointRef>
      <CommonName>Westfield Access Road</CommonName>
    </AnnotatedStopPointRef>
    <AnnotatedStopPointRef>
      <StopPointRef>6500D0690</StopPointRef>
      <CommonName>Forth View</CommonName>
    </AnnotatedStopPointRef>
    <AnnotatedStopPointRef>
      <StopPointRef>6500D0693</StopPointRef>
      <CommonName>Dewar Avenue</CommonName>
    </AnnotatedStopPointRef>
    <AnnotatedStopPointRef>
      <StopPointRef>6500D0688</StopPointRef>
      <CommonName>High Street Stance A</CommonName>
    </AnnotatedStopPointRef>
    <AnnotatedStopPointRef>
      <StopPointRef>6500D0686</StopPointRef>
      <CommonName>Kilbagie Street</CommonName>
    </AnnotatedStopPointRef>
    <AnnotatedStopPointRef>
      <StopPointRef>6500D0685</StopPointRef>
      <CommonName>Kirk Brae</CommonName>
    </AnnotatedStopPointRef>
    <AnnotatedStopPointRef>
      <StopPointRef>6500D0682</StopPointRef>
      <CommonName>Tulliallan Golf Course</CommonName>
    </AnnotatedStopPointRef>
    <AnnotatedStopPointRef>
      <StopPointRef>6500D0689</StopPointRef>
      <CommonName>High Street Stance B</CommonName>
    </AnnotatedStopPointRef>
    <AnnotatedStopPointRef>
      <StopPointRef>6500D9977</StopPointRef>
      <CommonName>West Lodge</CommonName>
    </AnnotatedStopPointRef>
    <AnnotatedStopPointRef>
      <StopPointRef>6500D1106</StopPointRef>
      <CommonName>Road End</CommonName>
    </AnnotatedStopPointRef>
    <AnnotatedStopPointRef>
      <StopPointRef>6500D0683</StopPointRef>
      <CommonName>Tulliallan Golf Course</CommonName>
    </AnnotatedStopPointRef>
    <AnnotatedStopPointRef>
      <StopPointRef>6500D0684</StopPointRef>
      <CommonName>Kirk Brae</CommonName>
    </AnnotatedStopPointRef>
    <AnnotatedStopPointRef>
      <StopPointRef>6500D0687</StopPointRef>
      <CommonName>Kilbagie Street</CommonName>
    </AnnotatedStopPointRef>
    <AnnotatedStopPointRef>
      <StopPointRef>6500D0692</StopPointRef>
      <CommonName>Dewar Avenue</CommonName>
    </AnnotatedStopPointRef>
    <AnnotatedStopPointRef>
      <StopPointRef>6500D0691</StopPointRef>
      <CommonName>Forth View</CommonName>
    </AnnotatedStopPointRef>
    <AnnotatedStopPointRef>
      <StopPointRef>6500D1104</StopPointRef>
      <CommonName>Westfield Access Road</CommonName>
    </AnnotatedStopPointRef>
    <AnnotatedStopPointRef>
      <StopPointRef>6500D9876</StopPointRef>
      <CommonName>Moorloch Road End</CommonName>
    </AnnotatedStopPointRef>
    <AnnotatedStopPointRef>
      <StopPointRef>6500D1109</StopPointRef>
      <CommonName>Primary School</CommonName>
    </AnnotatedStopPointRef>
    <AnnotatedStopPointRef>
      <StopPointRef>6500D0593</StopPointRef>
      <CommonName>Ordnance Road</CommonName>
    </AnnotatedStopPointRef>
    <AnnotatedStopPointRef>
      <StopPointRef>6500D9186</StopPointRef>
      <CommonName>Waulkmill Farm</CommonName>
    </AnnotatedStopPointRef>
    <AnnotatedStopPointRef>
      <StopPointRef>6500D9135</StopPointRef>
      <CommonName>East Lodge</CommonName>
    </AnnotatedStopPointRef>
    <AnnotatedStopPointRef>
      <StopPointRef>6500D9166</StopPointRef>
      <CommonName>Road End</CommonName>
    </AnnotatedStopPointRef>
    <AnnotatedStopPointRef>
      <StopPointRef>6500D9179</StopPointRef>
      <CommonName>Pattiesmuir Road End</CommonName>
    </AnnotatedStopPointRef>
    <AnnotatedStopPointRef>
      <StopPointRef>6500D0775</StopPointRef>
      <CommonName>Camdean Primary School</CommonName>
    </AnnotatedStopPointRef>
    <AnnotatedStopPointRef>
      <StopPointRef>6500D0773</StopPointRef>
      <CommonName>Albert Street</CommonName>
    </AnnotatedStopPointRef>
    <AnnotatedStopPointRef>
      <StopPointRef>6500D0776</StopPointRef>
      <CommonName>Park Road West</CommonName>
    </AnnotatedStopPointRef>
    <AnnotatedStopPointRef>
      <StopPointRef>6500D1071</StopPointRef>
      <CommonName>Railway Station</CommonName>
    </AnnotatedStopPointRef>
    <AnnotatedStopPointRef>
      <StopPointRef>6500D0729</StopPointRef>
      <CommonName>Carnegie Campus</CommonName>
    </AnnotatedStopPointRef>
    <AnnotatedStopPointRef>
      <StopPointRef>6500D0502</StopPointRef>
      <CommonName>Pitreavie Business Park</CommonName>
    </AnnotatedStopPointRef>
    <AnnotatedStopPointRef>
      <StopPointRef>6500D1027</StopPointRef>
      <CommonName>Pitreavie Playing Fields</CommonName>
    </AnnotatedStopPointRef>
    <AnnotatedStopPointRef>
      <StopPointRef>6500D0499</StopPointRef>
      <CommonName>Pitreavie Golf Course</CommonName>
    </AnnotatedStopPointRef>
    <AnnotatedStopPointRef>
      <StopPointRef>6500D0498</StopPointRef>
      <CommonName>Cypress Grove</CommonName>
    </AnnotatedStopPointRef>
    <AnnotatedStopPointRef>
      <StopPointRef>6500D1036</StopPointRef>
      <CommonName>King Malcolm Hotel</CommonName>
    </AnnotatedStopPointRef>
    <AnnotatedStopPointRef>
      <StopPointRef>6500D0444</StopPointRef>
      <CommonName>Cottage Inn</CommonName>
    </AnnotatedStopPointRef>
    <AnnotatedStopPointRef>
      <StopPointRef>6500D0435</StopPointRef>
      <CommonName>Dunfermline High School</CommonName>
    </AnnotatedStopPointRef>
  </StopPoints>
  <RouteSections>
    <RouteSection id="FIADF12_008">
      <RouteLink id="FIADF12_008_94525">
        <From>
          <StopPointRef>6500D9357</StopPointRef>
        </From>
        <To>
          <StopPointRef>6500D9238</StopPointRef>
        </To>
        <Direction>inbound</Direction>
      </RouteLink>
      <RouteLink id="FIADF12_008_94526">
        <From>
          <StopPointRef>6500D9238</StopPointRef>
        </From>
        <To>
          <StopPointRef>6500D0436</StopPointRef>
        </To>
        <Direction>inbound</Direction>
      </RouteLink>
      <RouteLink id="FIADF12_008_94527">
        <From>
          <StopPointRef>6500D0436</StopPointRef>
        </From>
        <To>
          <StopPointRef>6500D0428</StopPointRef>
        </To>
        <Direction>inbound</Direction>
      </RouteLink>
      <RouteLink id="FIADF12_008_94528">
        <From>
          <StopPointRef>6500D0428</StopPointRef>
        </From>
        <To>
          <StopPointRef>6500D1035</StopPointRef>
        </To>
        <Direction>inbound</Direction>
      </RouteLink>
      <RouteLink id="FIADF12_008_94529">
        <From>
          <StopPointRef>6500D1035</StopPointRef>
        </From>
        <To>
          <StopPointRef>6500D0497</StopPointRef>
        </To>
        <Direction>inbound</Direction>
      </RouteLink>
      <RouteLink id="FIADF12_008_94530">
        <From>
          <StopPointRef>6500D0497</StopPointRef>
        </From>
        <To>
          <StopPointRef>6500D0500</StopPointRef>
        </To>
        <Direction>inbound</Direction>
      </RouteLink>
      <RouteLink id="FIADF12_008_94531">
        <From>
          <StopPointRef>6500D0500</StopPointRef>
        </From>
        <To>
          <StopPointRef>6500D0916</StopPointRef>
        </To>
        <Direction>inbound</Direction>
      </RouteLink>
      <RouteLink id="FIADF12_008_94532">
        <From>
          <StopPointRef>6500D0916</StopPointRef>
        </From>
        <To>
          <StopPointRef>6500D0501</StopPointRef>
        </To>
        <Direction>inbound</Direction>
      </RouteLink>
      <RouteLink id="FIADF12_008_94533">
        <From>
          <StopPointRef>6500D0501</StopPointRef>
        </From>
        <To>
          <StopPointRef>6500D0243</StopPointRef>
        </To>
        <Direction>inbound</Direction>
      </RouteLink>
      <RouteLink id="FIADF12_008_94534">
        <From>
          <StopPointRef>6500D0243</StopPointRef>
        </From>
        <To>
          <StopPointRef>6500D0244</StopPointRef>
        </To>
        <Direction>inbound</Direction>
      </RouteLink>
      <RouteLink id="FIADF12_008_94535">
        <From>
          <StopPointRef>6500D0244</StopPointRef>
        </From>
        <To>
          <StopPointRef>6500D0774</StopPointRef>
        </To>
        <Direction>inbound</Direction>
      </RouteLink>
      <RouteLink id="FIADF12_008_94536">
        <From>
          <StopPointRef>6500D0774</StopPointRef>
        </From>
        <To>
          <StopPointRef>6500D1100</StopPointRef>
        </To>
        <Direction>inbound</Direction>
      </RouteLink>
      <RouteLink id="FIADF12_008_94537">
        <From>
          <StopPointRef>6500D1100</StopPointRef>
        </From>
        <To>
          <StopPointRef>6500D9180</StopPointRef>
        </To>
        <Direction>inbound</Direction>
      </RouteLink>
      <RouteLink id="FIADF12_008_94538">
        <From>
          <StopPointRef>6500D9180</StopPointRef>
        </From>
        <To>
          <StopPointRef>6500D9165</StopPointRef>
        </To>
        <Direction>inbound</Direction>
      </RouteLink>
      <RouteLink id="FIADF12_008_94539">
        <From>
          <StopPointRef>6500D9165</StopPointRef>
        </From>
        <To>
          <StopPointRef>6500D9182</StopPointRef>
        </To>
        <Direction>inbound</Direction>
      </RouteLink>
      <RouteLink id="FIADF12_008_94540">
        <From>
          <StopPointRef>6500D9182</StopPointRef>
        </From>
        <To>
          <StopPointRef>6500D9185</StopPointRef>
        </To>
        <Direction>inbound</Direction>
      </RouteLink>
      <RouteLink id="FIADF12_008_94541">
        <From>
          <StopPointRef>6500D9185</StopPointRef>
        </From>
        <To>
          <StopPointRef>6500D0594</StopPointRef>
        </To>
        <Direction>inbound</Direction>
      </RouteLink>
      <RouteLink id="FIADF12_008_94542">
        <From>
          <StopPointRef>6500D0594</StopPointRef>
        </From>
        <To>
          <StopPointRef>6500D1110</StopPointRef>
        </To>
        <Direction>inbound</Direction>
      </RouteLink>
      <RouteLink id="FIADF12_008_94543">
        <From>
          <StopPointRef>6500D1110</StopPointRef>
        </From>
        <To>
          <StopPointRef>6500D1105</StopPointRef>
        </To>
        <Direction>inbound</Direction>
      </RouteLink>
      <RouteLink id="FIADF12_008_94544">
        <From>
          <StopPointRef>6500D1105</StopPointRef>
        </From>
        <To>
          <StopPointRef>6500D0690</StopPointRef>
        </To>
        <Direction>inbound</Direction>
      </RouteLink>
      <RouteLink id="FIADF12_008_94545">
        <From>
          <StopPointRef>6500D0690</StopPointRef>
        </From>
        <To>
          <StopPointRef>6500D0693</StopPointRef>
        </To>
        <Direction>inbound</Direction>
      </RouteLink>
      <RouteLink id="FIADF12_008_94546">
        <From>
          <StopPointRef>6500D0693</StopPointRef>
        </From>
        <To>
          <StopPointRef>6500D0688</StopPointRef>
        </To>
        <Direction>inbound</Direction>
      </RouteLink>
      <RouteLink id="FIADF12_008_94547">
        <From>
          <StopPointRef>6500D0688</StopPointRef>
        </From>
        <To>
          <StopPointRef>6500D0686</StopPointRef>
        </To>
        <Direction>inbound</Direction>
      </RouteLink>
      <RouteLink id="FIADF12_008_94548">
        <From>
          <StopPointRef>6500D0686</StopPointRef>
        </From>
        <To>
          <StopPointRef>6500D0685</StopPointRef>
        </To>
        <Direction>inbound</Direction>
      </RouteLink>
      <RouteLink id="FIADF12_008_94549">
        <From>
          <StopPointRef>6500D0685</StopPointRef>
        </From>
        <To>
          <StopPointRef>6500D0682</StopPointRef>
        </To>
        <Direction>inbound</Direction>
      </RouteLink>
    </RouteSection>
    <RouteSection id="FIADF12_007">
      <RouteLink id="FIADF12_007_94551">
        <From>
          <StopPointRef>6500D0689</StopPointRef>
        </From>
        <To>
          <StopPointRef>6500D0686</StopPointRef>
        </To>
        <Direction>outbound</Direction>
      </RouteLink>
      <RouteLink id="FIADF12_007_94552">
        <From>
          <StopPointRef>6500D0686</StopPointRef>
        </From>
        <To>
          <StopPointRef>6500D0685</StopPointRef>
        </To>
        <Direction>outbound</Direction>
      </RouteLink>
      <RouteLink id="FIADF12_007_94553">
        <From>
          <StopPointRef>6500D0685</StopPointRef>
        </From>
        <To>
          <StopPointRef>6500D0682</StopPointRef>
        </To>
        <Direction>outbound</Direction>
      </RouteLink>
      <RouteLink id="FIADF12_007_94554">
        <From>
          <StopPointRef>6500D0682</StopPointRef>
        </From>
        <To>
          <StopPointRef>6500D9977</StopPointRef>
        </To>
        <Direction>outbound</Direction>
      </RouteLink>
      <RouteLink id="FIADF12_007_94555">
        <From>
          <StopPointRef>6500D9977</StopPointRef>
        </From>
        <To>
          <StopPointRef>6500D1106</StopPointRef>
        </To>
        <Direction>outbound</Direction>
      </RouteLink>
      <RouteLink id="FIADF12_007_94556">
        <From>
          <StopPointRef>6500D1106</StopPointRef>
        </From>
        <To>
          <StopPointRef>6500D0683</StopPointRef>
        </To>
        <Direction>outbound</Direction>
      </RouteLink>
      <RouteLink id="FIADF12_007_94557">
        <From>
          <StopPointRef>6500D0683</StopPointRef>
        </From>
        <To>
          <StopPointRef>6500D0684</StopPointRef>
        </To>
        <Direction>outbound</Direction>
      </RouteLink>
      <RouteLink id="FIADF12_007_94558">
        <From>
          <StopPointRef>6500D0684</StopPointRef>
        </From>
        <To>
          <StopPointRef>6500D0687</StopPointRef>
        </To>
        <Direction>outbound</Direction>
      </RouteLink>
      <RouteLink id="FIADF12_007_94559">
        <From>
          <StopPointRef>6500D0687</StopPointRef>
        </From>
        <To>
          <StopPointRef>6500D0692</StopPointRef>
        </To>
        <Direction>outbound</Direction>
      </RouteLink>
      <RouteLink id="FIADF12_007_94560">
        <From>
          <StopPointRef>6500D0692</StopPointRef>
        </From>
        <To>
          <StopPointRef>6500D0691</StopPointRef>
        </To>
        <Direction>outbound</Direction>
      </RouteLink>
      <RouteLink id="FIADF12_007_94561">
        <From>
          <StopPointRef>6500D0691</StopPointRef>
        </From>
        <To>
          <StopPointRef>6500D1104</StopPointRef>
        </To>
        <Direction>outbound</Direction>
      </RouteLink>
      <RouteLink id="FIADF12_007_94562">
        <From>
          <StopPointRef>6500D1104</StopPointRef>
        </From>
        <To>
          <StopPointRef>6500D9876</StopPointRef>
        </To>
        <Direction>outbound</Direction>
      </RouteLink>
      <RouteLink id="FIADF12_007_94563">
        <From>
          <StopPointRef>6500D9876</StopPointRef>
        </From>
        <To>
          <StopPointRef>6500D1109</StopPointRef>
        </To>
        <Direction>outbound</Direction>
      </RouteLink>
      <RouteLink id="FIADF12_007_94564">
        <From>
          <StopPointRef>6500D1109</StopPointRef>
        </From>
        <To>
          <StopPointRef>6500D0593</StopPointRef>
        </To>
        <Direction>outbound</Direction>
      </RouteLink>
      <RouteLink id="FIADF12_007_94565">
        <From>
          <StopPointRef>6500D0593</StopPointRef>
        </From>
        <To>
          <StopPointRef>6500D9186</StopPointRef>
        </To>
        <Direction>outbound</Direction>
      </RouteLink>
      <RouteLink id="FIADF12_007_94566">
        <From>
          <StopPointRef>6500D9186</StopPointRef>
        </From>
        <To>
          <StopPointRef>6500D9135</StopPointRef>
        </To>
        <Direction>outbound</Direction>
      </RouteLink>
      <RouteLink id="FIADF12_007_94567">
        <From>
          <StopPointRef>6500D9135</StopPointRef>
        </From>
        <To>
          <StopPointRef>6500D9166</StopPointRef>
        </To>
        <Direction>outbound</Direction>
      </RouteLink>
      <RouteLink id="FIADF12_007_94568">
        <From>
          <StopPointRef>6500D9166</StopPointRef>
        </From>
        <To>
          <StopPointRef>6500D9179</StopPointRef>
        </To>
        <Direction>outbound</Direction>
      </RouteLink>
      <RouteLink id="FIADF12_007_94569">
        <From>
          <StopPointRef>6500D9179</StopPointRef>
        </From>
        <To>
          <StopPointRef>6500D0775</StopPointRef>
        </To>
        <Direction>outbound</Direction>
      </RouteLink>
      <RouteLink id="FIADF12_007_94570">
        <From>
          <StopPointRef>6500D0775</StopPointRef>
        </From>
        <To>
          <StopPointRef>6500D0773</StopPointRef>
        </To>
        <Direction>outbound</Direction>
      </RouteLink>
      <RouteLink id="FIADF12_007_94571">
        <From>
          <StopPointRef>6500D0773</StopPointRef>
        </From>
        <To>
          <StopPointRef>6500D0776</StopPointRef>
        </To>
        <Direction>outbound</Direction>
      </RouteLink>
      <RouteLink id="FIADF12_007_94572">
        <From>
          <StopPointRef>6500D0776</StopPointRef>
        </From>
        <To>
          <StopPointRef>6500D1071</StopPointRef>
        </To>
        <Direction>outbound</Direction>
      </RouteLink>
      <RouteLink id="FIADF12_007_94573">
        <From>
          <StopPointRef>6500D1071</StopPointRef>
        </From>
        <To>
          <StopPointRef>6500D0729</StopPointRef>
        </To>
        <Direction>outbound</Direction>
      </RouteLink>
      <RouteLink id="FIADF12_007_94574">
        <From>
          <StopPointRef>6500D0729</StopPointRef>
        </From>
        <To>
          <StopPointRef>6500D0502</StopPointRef>
        </To>
        <Direction>outbound</Direction>
      </RouteLink>
      <RouteLink id="FIADF12_007_94575">
        <From>
          <StopPointRef>6500D0502</StopPointRef>
        </From>
        <To>
          <StopPointRef>6500D1027</StopPointRef>
        </To>
        <Direction>outbound</Direction>
      </RouteLink>
      <RouteLink id="FIADF12_007_94576">
        <From>
          <StopPointRef>6500D1027</StopPointRef>
        </From>
        <To>
          <StopPointRef>6500D0499</StopPointRef>
        </To>
        <Direction>outbound</Direction>
      </RouteLink>
      <RouteLink id="FIADF12_007_94577">
        <From>
          <StopPointRef>6500D0499</StopPointRef>
        </From>
        <To>
          <StopPointRef>6500D0498</StopPointRef>
        </To>
        <Direction>outbound</Direction>
      </RouteLink>
      <RouteLink id="FIADF12_007_94578">
        <From>
          <StopPointRef>6500D0498</StopPointRef>
        </From>
        <To>
          <StopPointRef>6500D1036</StopPointRef>
        </To>
        <Direction>outbound</Direction>
      </RouteLink>
      <RouteLink id="FIADF12_007_94579">
        <From>
          <StopPointRef>6500D1036</StopPointRef>
        </From>
        <To>
          <StopPointRef>6500D0444</StopPointRef>
        </To>
        <Direction>outbound</Direction>
      </RouteLink>
      <RouteLink id="FIADF12_007_94580">
        <From>
          <StopPointRef>6500D0444</StopPointRef>
        </From>
        <To>
          <StopPointRef>6500D0435</StopPointRef>
        </To>
        <Direction>outbound</Direction>
      </RouteLink>
      <RouteLink id="FIADF12_007_94581">
        <From>
          <StopPointRef>6500D0435</StopPointRef>
        </From>
        <To>
          <StopPointRef>6500D9357</StopPointRef>
        </To>
        <Direction>outbound</Direction>
      </RouteLink>
    </RouteSection>
  </RouteSections>
  <Routes>
    <Route id="FIADF12_008">
      <Description>Dunfermline High Sch - Kincardine
</Description>
      <RouteSectionRef>FIADF12_008</RouteSectionRef>
    </Route>
    <Route id="FIADF12_007">
      <Description>Kincardine - Dunfermline High Sch
</Description>
      <RouteSectionRef>FIADF12_007</RouteSectionRef>
    </Route>
  </Routes>
  <JourneyPatternSections>
    <JourneyPatternSection id="JPS_FIADF12-3">
      <JourneyPatternTimingLink id="JPS_FIADF12-3_94525">
        <From>
          <StopPointRef>6500D9357</StopPointRef>
          <TimingStatus>PTP</TimingStatus>
        </From>
        <To>
          <StopPointRef>6500D9238</StopPointRef>
          <TimingStatus>PTP</TimingStatus>
        </To>
        <RouteLinkRef>FIADF12_008_94525</RouteLinkRef>
        <Direction>inbound</Direction>
        <RunTime>PT900S</RunTime>
      </JourneyPatternTimingLink>
      <JourneyPatternTimingLink id="JPS_FIADF12-3_94526">
        <From>
          <StopPointRef>6500D9238</StopPointRef>
          <TimingStatus>PTP</TimingStatus>
        </From>
        <To>
          <StopPointRef>6500D0436</StopPointRef>
          <TimingStatus>OTH</TimingStatus>
        </To>
        <RouteLinkRef>FIADF12_008_94526</RouteLinkRef>
        <Direction>inbound</Direction>
        <RunTime>PT0S</RunTime>
      </JourneyPatternTimingLink>
      <JourneyPatternTimingLink id="JPS_FIADF12-3_94527">
        <From>
          <StopPointRef>6500D0436</StopPointRef>
          <TimingStatus>OTH</TimingStatus>
        </From>
        <To>
          <StopPointRef>6500D0428</StopPointRef>
          <TimingStatus>OTH</TimingStatus>
        </To>
        <RouteLinkRef>FIADF12_008_94527</RouteLinkRef>
        <Direction>inbound</Direction>
        <RunTime>PT0S</RunTime>
      </JourneyPatternTimingLink>
      <JourneyPatternTimingLink id="JPS_FIADF12-3_94528">
        <From>
          <StopPointRef>6500D0428</StopPointRef>
          <TimingStatus>OTH</TimingStatus>
        </From>
        <To>
          <StopPointRef>6500D1035</StopPointRef>
          <TimingStatus>OTH</TimingStatus>
        </To>
        <RouteLinkRef>FIADF12_008_94528</RouteLinkRef>
        <Direction>inbound</Direction>
        <RunTime>PT360S</RunTime>
      </JourneyPatternTimingLink>
      <JourneyPatternTimingLink id="JPS_FIADF12-3_94529">
        <From>
          <StopPointRef>6500D1035</StopPointRef>
          <TimingStatus>OTH</TimingStatus>
        </From>
        <To>
          <StopPointRef>6500D0497</StopPointRef>
          <TimingStatus>OTH</TimingStatus>
        </To>
        <RouteLinkRef>FIADF12_008_94529</RouteLinkRef>
        <Direction>inbound</Direction>
        <RunTime>PT60S</RunTime>
      </JourneyPatternTimingLink>
      <JourneyPatternTimingLink id="JPS_FIADF12-3_94530">
        <From>
          <StopPointRef>6500D0497</StopPointRef>
          <TimingStatus>OTH</TimingStatus>
        </From>
        <To>
          <StopPointRef>6500D0500</StopPointRef>
          <TimingStatus>OTH</TimingStatus>
        </To>
        <RouteLinkRef>FIADF12_008_94530</RouteLinkRef>
        <Direction>inbound</Direction>
        <RunTime>PT0S</RunTime>
      </JourneyPatternTimingLink>
      <JourneyPatternTimingLink id="JPS_FIADF12-3_94531">
        <From>
          <StopPointRef>6500D0500</StopPointRef>
          <TimingStatus>OTH</TimingStatus>
        </From>
        <To>
          <StopPointRef>6500D0916</StopPointRef>
          <TimingStatus>OTH</TimingStatus>
        </To>
        <RouteLinkRef>FIADF12_008_94531</RouteLinkRef>
        <Direction>inbound</Direction>
        <RunTime>PT0S</RunTime>
      </JourneyPatternTimingLink>
      <JourneyPatternTimingLink id="JPS_FIADF12-3_94532">
        <From>
          <StopPointRef>6500D0916</StopPointRef>
          <TimingStatus>OTH</TimingStatus>
        </From>
        <To>
          <StopPointRef>6500D0501</StopPointRef>
          <TimingStatus>OTH</TimingStatus>
        </To>
        <RouteLinkRef>FIADF12_008_94532</RouteLinkRef>
        <Direction>inbound</Direction>
        <RunTime>PT0S</RunTime>
      </JourneyPatternTimingLink>
      <JourneyPatternTimingLink id="JPS_FIADF12-3_94533">
        <From>
          <StopPointRef>6500D0501</StopPointRef>
          <TimingStatus>OTH</TimingStatus>
        </From>
        <To>
          <StopPointRef>6500D0243</StopPointRef>
          <TimingStatus>OTH</TimingStatus>
        </To>
        <RouteLinkRef>FIADF12_008_94533</RouteLinkRef>
        <Direction>inbound</Direction>
        <RunTime>PT0S</RunTime>
      </JourneyPatternTimingLink>
      <JourneyPatternTimingLink id="JPS_FIADF12-3_94534">
        <From>
          <StopPointRef>6500D0243</StopPointRef>
          <TimingStatus>OTH</TimingStatus>
        </From>
        <To>
          <StopPointRef>6500D0244</StopPointRef>
          <TimingStatus>OTH</TimingStatus>
        </To>
        <RouteLinkRef>FIADF12_008_94534</RouteLinkRef>
        <Direction>inbound</Direction>
        <RunTime>PT60S</RunTime>
      </JourneyPatternTimingLink>
      <JourneyPatternTimingLink id="JPS_FIADF12-3_94535">
        <From>
          <StopPointRef>6500D0244</StopPointRef>
          <TimingStatus>OTH</TimingStatus>
        </From>
        <To>
          <StopPointRef>6500D0774</StopPointRef>
          <TimingStatus>PTP</TimingStatus>
        </To>
        <RouteLinkRef>FIADF12_008_94535</RouteLinkRef>
        <Direction>inbound</Direction>
        <RunTime>PT60S</RunTime>
      </JourneyPatternTimingLink>
      <JourneyPatternTimingLink id="JPS_FIADF12-3_94536">
        <From>
          <StopPointRef>6500D0774</StopPointRef>
          <TimingStatus>PTP</TimingStatus>
        </From>
        <To>
          <StopPointRef>6500D1100</StopPointRef>
          <TimingStatus>OTH</TimingStatus>
        </To>
        <RouteLinkRef>FIADF12_008_94536</RouteLinkRef>
        <Direction>inbound</Direction>
        <RunTime>PT180S</RunTime>
      </JourneyPatternTimingLink>
      <JourneyPatternTimingLink id="JPS_FIADF12-3_94537">
        <From>
          <StopPointRef>6500D1100</StopPointRef>
          <TimingStatus>OTH</TimingStatus>
        </From>
        <To>
          <StopPointRef>6500D9180</StopPointRef>
          <TimingStatus>OTH</TimingStatus>
        </To>
        <RouteLinkRef>FIADF12_008_94537</RouteLinkRef>
        <Direction>inbound</Direction>
        <RunTime>PT60S</RunTime>
      </JourneyPatternTimingLink>
      <JourneyPatternTimingLink id="JPS_FIADF12-3_94538">
        <From>
          <StopPointRef>6500D9180</StopPointRef>
          <TimingStatus>OTH</TimingStatus>
        </From>
        <To>
          <StopPointRef>6500D9165</StopPointRef>
          <TimingStatus>OTH</TimingStatus>
        </To>
        <RouteLinkRef>FIADF12_008_94538</RouteLinkRef>
        <Direction>inbound</Direction>
        <RunTime>PT0S</RunTime>
      </JourneyPatternTimingLink>
      <JourneyPatternTimingLink id="JPS_FIADF12-3_94539">
        <From>
          <StopPointRef>6500D9165</StopPointRef>
          <TimingStatus>OTH</TimingStatus>
        </From>
        <To>
          <StopPointRef>6500D9182</StopPointRef>
          <TimingStatus>OTH</TimingStatus>
        </To>
        <RouteLinkRef>FIADF12_008_94539</RouteLinkRef>
        <Direction>inbound</Direction>
        <RunTime>PT60S</RunTime>
      </JourneyPatternTimingLink>
      <JourneyPatternTimingLink id="JPS_FIADF12-3_94540">
        <From>
          <StopPointRef>6500D9182</StopPointRef>
          <TimingStatus>OTH</TimingStatus>
        </From>
        <To>
          <StopPointRef>6500D9185</StopPointRef>
          <TimingStatus>OTH</TimingStatus>
        </To>
        <RouteLinkRef>FIADF12_008_94540</RouteLinkRef>
        <Direction>inbound</Direction>
        <RunTime>PT60S</RunTime>
      </JourneyPatternTimingLink>
      <JourneyPatternTimingLink id="JPS_FIADF12-3_94541">
        <From>
          <StopPointRef>6500D9185</StopPointRef>
          <TimingStatus>OTH</TimingStatus>
        </From>
        <To>
          <StopPointRef>6500D0594</StopPointRef>
          <TimingStatus>PTP</TimingStatus>
        </To>
        <RouteLinkRef>FIADF12_008_94541</RouteLinkRef>
        <Direction>inbound</Direction>
        <RunTime>PT60S</RunTime>
      </JourneyPatternTimingLink>
      <JourneyPatternTimingLink id="JPS_FIADF12-3_94542">
        <From>
          <StopPointRef>6500D0594</StopPointRef>
          <TimingStatus>PTP</TimingStatus>
        </From>
        <To>
          <StopPointRef>6500D1110</StopPointRef>
          <TimingStatus>OTH</TimingStatus>
        </To>
        <RouteLinkRef>FIADF12_008_94542</RouteLinkRef>
        <Direction>inbound</Direction>
        <RunTime>PT0S</RunTime>
      </JourneyPatternTimingLink>
      <JourneyPatternTimingLink id="JPS_FIADF12-3_94543">
        <From>
          <StopPointRef>6500D1110</StopPointRef>
          <TimingStatus>OTH</TimingStatus>
        </From>
        <To>
          <StopPointRef>6500D1105</StopPointRef>
          <TimingStatus>OTH</TimingStatus>
        </To>
        <RouteLinkRef>FIADF12_008_94543</RouteLinkRef>
        <Direction>inbound</Direction>
        <RunTime>PT660S</RunTime>
      </JourneyPatternTimingLink>
      <JourneyPatternTimingLink id="JPS_FIADF12-3_94544">
        <From>
          <StopPointRef>6500D1105</StopPointRef>
          <TimingStatus>OTH</TimingStatus>
        </From>
        <To>
          <StopPointRef>6500D0690</StopPointRef>
          <TimingStatus>PTP</TimingStatus>
        </To>
        <RouteLinkRef>FIADF12_008_94544</RouteLinkRef>
        <Direction>inbound</Direction>
        <RunTime>PT60S</RunTime>
      </JourneyPatternTimingLink>
      <JourneyPatternTimingLink id="JPS_FIADF12-3_94545">
        <From>
          <StopPointRef>6500D0690</StopPointRef>
          <TimingStatus>PTP</TimingStatus>
        </From>
        <To>
          <StopPointRef>6500D0693</StopPointRef>
          <TimingStatus>OTH</TimingStatus>
        </To>
        <RouteLinkRef>FIADF12_008_94545</RouteLinkRef>
        <Direction>inbound</Direction>
        <RunTime>PT0S</RunTime>
      </JourneyPatternTimingLink>
      <JourneyPatternTimingLink id="JPS_FIADF12-3_94546">
        <From>
          <StopPointRef>6500D0693</StopPointRef>
          <TimingStatus>OTH</TimingStatus>
        </From>
        <To>
          <StopPointRef>6500D0688</StopPointRef>
          <TimingStatus>PTP</TimingStatus>
        </To>
        <RouteLinkRef>FIADF12_008_94546</RouteLinkRef>
        <Direction>inbound</Direction>
        <RunTime>PT120S</RunTime>
      </JourneyPatternTimingLink>
      <JourneyPatternTimingLink id="JPS_FIADF12-3_94547">
        <From>
          <StopPointRef>6500D0688</StopPointRef>
          <TimingStatus>PTP</TimingStatus>
        </From>
        <To>
          <StopPointRef>6500D0686</StopPointRef>
          <TimingStatus>OTH</TimingStatus>
        </To>
        <RouteLinkRef>FIADF12_008_94547</RouteLinkRef>
        <Direction>inbound</Direction>
        <RunTime>PT60S</RunTime>
      </JourneyPatternTimingLink>
      <JourneyPatternTimingLink id="JPS_FIADF12-3_94548">
        <From>
          <StopPointRef>6500D0686</StopPointRef>
          <TimingStatus>OTH</TimingStatus>
        </From>
        <To>
          <StopPointRef>6500D0685</StopPointRef>
          <TimingStatus>OTH</TimingStatus>
        </To>
        <RouteLinkRef>FIADF12_008_94548</RouteLinkRef>
        <Direction>inbound</Direction>
        <RunTime>PT60S</RunTime>
      </JourneyPatternTimingLink>
      <JourneyPatternTimingLink id="JPS_FIADF12-3_94549">
        <From>
          <StopPointRef>6500D0685</StopPointRef>
          <TimingStatus>OTH</TimingStatus>
        </From>
        <To>
          <StopPointRef>6500D0682</StopPointRef>
          <TimingStatus>PTP</TimingStatus>
        </To>
        <RouteLinkRef>FIADF12_008_94549</RouteLinkRef>
        <Direction>inbound</Direction>
        <RunTime>PT60S</RunTime>
      </JourneyPatternTimingLink>
    </JourneyPatternSection>
    <JourneyPatternSection id="JPS_FIADF12-4">
      <JourneyPatternTimingLink id="JPS_FIADF12-4_94551">
        <From>
          <StopPointRef>6500D0689</StopPointRef>
          <TimingStatus>PTP</TimingStatus>
        </From>
        <To>
          <StopPointRef>6500D0686</StopPointRef>
          <TimingStatus>OTH</TimingStatus>
        </To>
        <RouteLinkRef>FIADF12_007_94551</RouteLinkRef>
        <Direction>outbound</Direction>
        <RunTime>PT60S</RunTime>
      </JourneyPatternTimingLink>
      <JourneyPatternTimingLink id="JPS_FIADF12-4_94552">
        <From>
          <StopPointRef>6500D0686</StopPointRef>
          <TimingStatus>OTH</TimingStatus>
        </From>
        <To>
          <StopPointRef>6500D0685</StopPointRef>
          <TimingStatus>OTH</TimingStatus>
        </To>
        <RouteLinkRef>FIADF12_007_94552</RouteLinkRef>
        <Direction>outbound</Direction>
        <RunTime>PT60S</RunTime>
      </JourneyPatternTimingLink>
      <JourneyPatternTimingLink id="JPS_FIADF12-4_94553">
        <From>
          <StopPointRef>6500D0685</StopPointRef>
          <TimingStatus>OTH</TimingStatus>
        </From>
        <To>
          <StopPointRef>6500D0682</StopPointRef>
          <TimingStatus>PTP</TimingStatus>
        </To>
        <RouteLinkRef>FIADF12_007_94553</RouteLinkRef>
        <Direction>outbound</Direction>
        <RunTime>PT60S</RunTime>
      </JourneyPatternTimingLink>
      <JourneyPatternTimingLink id="JPS_FIADF12-4_94554">
        <From>
          <StopPointRef>6500D0682</StopPointRef>
          <TimingStatus>PTP</TimingStatus>
        </From>
        <To>
          <StopPointRef>6500D9977</StopPointRef>
          <TimingStatus>OTH</TimingStatus>
        </To>
        <RouteLinkRef>FIADF12_007_94554</RouteLinkRef>
        <Direction>outbound</Direction>
        <RunTime>PT120S</RunTime>
      </JourneyPatternTimingLink>
      <JourneyPatternTimingLink id="JPS_FIADF12-4_94555">
        <From>
          <StopPointRef>6500D9977</StopPointRef>
          <TimingStatus>OTH</TimingStatus>
        </From>
        <To>
          <StopPointRef>6500D1106</StopPointRef>
          <TimingStatus>OTH</TimingStatus>
        </To>
        <RouteLinkRef>FIADF12_007_94555</RouteLinkRef>
        <Direction>outbound</Direction>
        <RunTime>PT0S</RunTime>
      </JourneyPatternTimingLink>
      <JourneyPatternTimingLink id="JPS_FIADF12-4_94556">
        <From>
          <StopPointRef>6500D1106</StopPointRef>
          <TimingStatus>OTH</TimingStatus>
        </From>
        <To>
          <StopPointRef>6500D0683</StopPointRef>
          <TimingStatus>OTH</TimingStatus>
        </To>
        <RouteLinkRef>FIADF12_007_94556</RouteLinkRef>
        <Direction>outbound</Direction>
        <RunTime>PT120S</RunTime>
      </JourneyPatternTimingLink>
      <JourneyPatternTimingLink id="JPS_FIADF12-4_94557">
        <From>
          <StopPointRef>6500D0683</StopPointRef>
          <TimingStatus>OTH</TimingStatus>
        </From>
        <To>
          <StopPointRef>6500D0684</StopPointRef>
          <TimingStatus>OTH</TimingStatus>
        </To>
        <RouteLinkRef>FIADF12_007_94557</RouteLinkRef>
        <Direction>outbound</Direction>
        <RunTime>PT60S</RunTime>
      </JourneyPatternTimingLink>
      <JourneyPatternTimingLink id="JPS_FIADF12-4_94558">
        <From>
          <StopPointRef>6500D0684</StopPointRef>
          <TimingStatus>OTH</TimingStatus>
        </From>
        <To>
          <StopPointRef>6500D0687</StopPointRef>
          <TimingStatus>OTH</TimingStatus>
        </To>
        <RouteLinkRef>FIADF12_007_94558</RouteLinkRef>
        <Direction>outbound</Direction>
        <RunTime>PT0S</RunTime>
      </JourneyPatternTimingLink>
      <JourneyPatternTimingLink id="JPS_FIADF12-4_94559">
        <From>
          <StopPointRef>6500D0687</StopPointRef>
          <TimingStatus>OTH</TimingStatus>
        </From>
        <To>
          <StopPointRef>6500D0692</StopPointRef>
          <TimingStatus>OTH</TimingStatus>
        </To>
        <RouteLinkRef>FIADF12_007_94559</RouteLinkRef>
        <Direction>outbound</Direction>
        <RunTime>PT60S</RunTime>
      </JourneyPatternTimingLink>
      <JourneyPatternTimingLink id="JPS_FIADF12-4_94560">
        <From>
          <StopPointRef>6500D0692</StopPointRef>
          <TimingStatus>OTH</TimingStatus>
        </From>
        <To>
          <StopPointRef>6500D0691</StopPointRef>
          <TimingStatus>PTP</TimingStatus>
        </To>
        <RouteLinkRef>FIADF12_007_94560</RouteLinkRef>
        <Direction>outbound</Direction>
        <RunTime>PT60S</RunTime>
      </JourneyPatternTimingLink>
      <JourneyPatternTimingLink id="JPS_FIADF12-4_94561">
        <From>
          <StopPointRef>6500D0691</StopPointRef>
          <TimingStatus>PTP</TimingStatus>
        </From>
        <To>
          <StopPointRef>6500D1104</StopPointRef>
          <TimingStatus>OTH</TimingStatus>
        </To>
        <RouteLinkRef>FIADF12_007_94561</RouteLinkRef>
        <Direction>outbound</Direction>
        <RunTime>PT0S</RunTime>
      </JourneyPatternTimingLink>
      <JourneyPatternTimingLink id="JPS_FIADF12-4_94562">
        <From>
          <StopPointRef>6500D1104</StopPointRef>
          <TimingStatus>OTH</TimingStatus>
        </From>
        <To>
          <StopPointRef>6500D9876</StopPointRef>
          <TimingStatus>OTH</TimingStatus>
        </To>
        <RouteLinkRef>FIADF12_007_94562</RouteLinkRef>
        <Direction>outbound</Direction>
        <RunTime>PT60S</RunTime>
      </JourneyPatternTimingLink>
      <JourneyPatternTimingLink id="JPS_FIADF12-4_94563">
        <From>
          <StopPointRef>6500D9876</StopPointRef>
          <TimingStatus>OTH</TimingStatus>
        </From>
        <To>
          <StopPointRef>6500D1109</StopPointRef>
          <TimingStatus>OTH</TimingStatus>
        </To>
        <RouteLinkRef>FIADF12_007_94563</RouteLinkRef>
        <Direction>outbound</Direction>
        <RunTime>PT600S</RunTime>
      </JourneyPatternTimingLink>
      <JourneyPatternTimingLink id="JPS_FIADF12-4_94564">
        <From>
          <StopPointRef>6500D1109</StopPointRef>
          <TimingStatus>OTH</TimingStatus>
        </From>
        <To>
          <StopPointRef>6500D0593</StopPointRef>
          <TimingStatus>PTP</TimingStatus>
        </To>
        <RouteLinkRef>FIADF12_007_94564</RouteLinkRef>
        <Direction>outbound</Direction>
        <RunTime>PT60S</RunTime>
      </JourneyPatternTimingLink>
      <JourneyPatternTimingLink id="JPS_FIADF12-4_94565">
        <From>
          <StopPointRef>6500D0593</StopPointRef>
          <TimingStatus>PTP</TimingStatus>
        </From>
        <To>
          <StopPointRef>6500D9186</StopPointRef>
          <TimingStatus>OTH</TimingStatus>
        </To>
        <RouteLinkRef>FIADF12_007_94565</RouteLinkRef>
        <Direction>outbound</Direction>
        <RunTime>PT0S</RunTime>
      </JourneyPatternTimingLink>
      <JourneyPatternTimingLink id="JPS_FIADF12-4_94566">
        <From>
          <StopPointRef>6500D9186</StopPointRef>
          <TimingStatus>OTH</TimingStatus>
        </From>
        <To>
          <StopPointRef>6500D9135</StopPointRef>
          <TimingStatus>OTH</TimingStatus>
        </To>
        <RouteLinkRef>FIADF12_007_94566</RouteLinkRef>
        <Direction>outbound</Direction>
        <RunTime>PT180S</RunTime>
      </JourneyPatternTimingLink>
      <JourneyPatternTimingLink id="JPS_FIADF12-4_94567">
        <From>
          <StopPointRef>6500D9135</StopPointRef>
          <TimingStatus>OTH</TimingStatus>
        </From>
        <To>
          <StopPointRef>6500D9166</StopPointRef>
          <TimingStatus>OTH</TimingStatus>
        </To>
        <RouteLinkRef>FIADF12_007_94567</RouteLinkRef>
        <Direction>outbound</Direction>
        <RunTime>PT0S</RunTime>
      </JourneyPatternTimingLink>
      <JourneyPatternTimingLink id="JPS_FIADF12-4_94568">
        <From>
          <StopPointRef>6500D9166</StopPointRef>
          <TimingStatus>OTH</TimingStatus>
        </From>
        <To>
          <StopPointRef>6500D9179</StopPointRef>
          <TimingStatus>OTH</TimingStatus>
        </To>
        <RouteLinkRef>FIADF12_007_94568</RouteLinkRef>
        <Direction>outbound</Direction>
        <RunTime>PT0S</RunTime>
      </JourneyPatternTimingLink>
      <JourneyPatternTimingLink id="JPS_FIADF12-4_94569">
        <From>
          <StopPointRef>6500D9179</StopPointRef>
          <TimingStatus>OTH</TimingStatus>
        </From>
        <To>
          <StopPointRef>6500D0775</StopPointRef>
          <TimingStatus>OTH</TimingStatus>
        </To>
        <RouteLinkRef>FIADF12_007_94569</RouteLinkRef>
        <Direction>outbound</Direction>
        <RunTime>PT120S</RunTime>
      </JourneyPatternTimingLink>
      <JourneyPatternTimingLink id="JPS_FIADF12-4_94570">
        <From>
          <StopPointRef>6500D0775</StopPointRef>
          <TimingStatus>OTH</TimingStatus>
        </From>
        <To>
          <StopPointRef>6500D0773</StopPointRef>
          <TimingStatus>PTP</TimingStatus>
        </To>
        <RouteLinkRef>FIADF12_007_94570</RouteLinkRef>
        <Direction>outbound</Direction>
        <RunTime>PT60S</RunTime>
      </JourneyPatternTimingLink>
      <JourneyPatternTimingLink id="JPS_FIADF12-4_94571">
        <From>
          <StopPointRef>6500D0773</StopPointRef>
          <TimingStatus>PTP</TimingStatus>
        </From>
        <To>
          <StopPointRef>6500D0776</StopPointRef>
          <TimingStatus>OTH</TimingStatus>
        </To>
        <RouteLinkRef>FIADF12_007_94571</RouteLinkRef>
        <Direction>outbound</Direction>
        <RunTime>PT60S</RunTime>
      </JourneyPatternTimingLink>
      <JourneyPatternTimingLink id="JPS_FIADF12-4_94572">
        <From>
          <StopPointRef>6500D0776</StopPointRef>
          <TimingStatus>OTH</TimingStatus>
        </From>
        <To>
          <StopPointRef>6500D1071</StopPointRef>
          <TimingStatus>OTH</TimingStatus>
        </To>
        <RouteLinkRef>FIADF12_007_94572</RouteLinkRef>
        <Direction>outbound</Direction>
        <RunTime>PT60S</RunTime>
      </JourneyPatternTimingLink>
      <JourneyPatternTimingLink id="JPS_FIADF12-4_94573">
        <From>
          <StopPointRef>6500D1071</StopPointRef>
          <TimingStatus>OTH</TimingStatus>
        </From>
        <To>
          <StopPointRef>6500D0729</StopPointRef>
          <TimingStatus>OTH</TimingStatus>
        </To>
        <RouteLinkRef>FIADF12_007_94573</RouteLinkRef>
        <Direction>outbound</Direction>
        <RunTime>PT120S</RunTime>
      </JourneyPatternTimingLink>
      <JourneyPatternTimingLink id="JPS_FIADF12-4_94574">
        <From>
          <StopPointRef>6500D0729</StopPointRef>
          <TimingStatus>OTH</TimingStatus>
        </From>
        <To>
          <StopPointRef>6500D0502</StopPointRef>
          <TimingStatus>OTH</TimingStatus>
        </To>
        <RouteLinkRef>FIADF12_007_94574</RouteLinkRef>
        <Direction>outbound</Direction>
        <RunTime>PT60S</RunTime>
      </JourneyPatternTimingLink>
      <JourneyPatternTimingLink id="JPS_FIADF12-4_94575">
        <From>
          <StopPointRef>6500D0502</StopPointRef>
          <TimingStatus>OTH</TimingStatus>
        </From>
        <To>
          <StopPointRef>6500D1027</StopPointRef>
          <TimingStatus>OTH</TimingStatus>
        </To>
        <RouteLinkRef>FIADF12_007_94575</RouteLinkRef>
        <Direction>outbound</Direction>
        <RunTime>PT60S</RunTime>
      </JourneyPatternTimingLink>
      <JourneyPatternTimingLink id="JPS_FIADF12-4_94576">
        <From>
          <StopPointRef>6500D1027</StopPointRef>
          <TimingStatus>OTH</TimingStatus>
        </From>
        <To>
          <StopPointRef>6500D0499</StopPointRef>
          <TimingStatus>OTH</TimingStatus>
        </To>
        <RouteLinkRef>FIADF12_007_94576</RouteLinkRef>
        <Direction>outbound</Direction>
        <RunTime>PT60S</RunTime>
      </JourneyPatternTimingLink>
      <JourneyPatternTimingLink id="JPS_FIADF12-4_94577">
        <From>
          <StopPointRef>6500D0499</StopPointRef>
          <TimingStatus>OTH</TimingStatus>
        </From>
        <To>
          <StopPointRef>6500D0498</StopPointRef>
          <TimingStatus>OTH</TimingStatus>
        </To>
        <RouteLinkRef>FIADF12_007_94577</RouteLinkRef>
        <Direction>outbound</Direction>
        <RunTime>PT60S</RunTime>
      </JourneyPatternTimingLink>
      <JourneyPatternTimingLink id="JPS_FIADF12-4_94578">
        <From>
          <StopPointRef>6500D0498</StopPointRef>
          <TimingStatus>OTH</TimingStatus>
        </From>
        <To>
          <StopPointRef>6500D1036</StopPointRef>
          <TimingStatus>OTH</TimingStatus>
        </To>
        <RouteLinkRef>FIADF12_007_94578</RouteLinkRef>
        <Direction>outbound</Direction>
        <RunTime>PT120S</RunTime>
      </JourneyPatternTimingLink>
      <JourneyPatternTimingLink id="JPS_FIADF12-4_94579">
        <From>
          <StopPointRef>6500D1036</StopPointRef>
          <TimingStatus>OTH</TimingStatus>
        </From>
        <To>
          <StopPointRef>6500D0444</StopPointRef>
          <TimingStatus>OTH</TimingStatus>
        </To>
        <RouteLinkRef>FIADF12_007_94579</RouteLinkRef>
        <Direction>outbound</Direction>
        <RunTime>PT60S</RunTime>
      </JourneyPatternTimingLink>
      <JourneyPatternTimingLink id="JPS_FIADF12-4_94580">
        <From>
          <StopPointRef>6500D0444</StopPointRef>
          <TimingStatus>OTH</TimingStatus>
        </From>
        <To>
          <StopPointRef>6500D0435</StopPointRef>
          <TimingStatus>OTH</TimingStatus>
        </To>
        <RouteLinkRef>FIADF12_007_94580</RouteLinkRef>
        <Direction>outbound</Direction>
        <RunTime>PT120S</RunTime>
      </JourneyPatternTimingLink>
      <JourneyPatternTimingLink id="JPS_FIADF12-4_94581">
        <From>
          <StopPointRef>6500D0435</StopPointRef>
          <TimingStatus>OTH</TimingStatus>
        </From>
        <To>
          <StopPointRef>6500D9357</StopPointRef>
          <TimingStatus>PTP</TimingStatus>
        </To>
        <RouteLinkRef>FIADF12_007_94581</RouteLinkRef>
        <Direction>outbound</Direction>
        <RunTime>PT120S</RunTime>
      </JourneyPatternTimingLink>
    </JourneyPatternSection>
  </JourneyPatternSections>
  <Operators>
    <Operator id="SIF">
      <NationalOperatorCode>SCFI</NationalOperatorCode>
      <OperatorCode>SIF</OperatorCode>
      <OperatorShortName>Stagecoach East Scotland</OperatorShortName>
    </Operator>
  </Operators>
  <Services>
    <Service>
      <ServiceCode>FIADF12</ServiceCode>
      <Lines>
        <Line id="0">
          <LineName>DF12</LineName>
        </Line>
      </Lines>
      <OperatingPeriod>
        <StartDate>2018-08-13</StartDate>
        <EndDate>2028-08-13</EndDate>
      </OperatingPeriod>
      <RegisteredOperatorRef>SIF</RegisteredOperatorRef>
      <StopRequirements>
        <NoNewStopsRequired />
      </StopRequirements>
      <Mode>bus</Mode>
      <Description>Kincardine - Dunfermline High Sch</Description>
      <StandardService>
        <Origin>Kincardine</Origin>
        <Destination>Dunfermline High Sch</Destination>
        <JourneyPattern id="JPS_FIADF12-3">
          <Direction>inbound</Direction>
          <JourneyPatternSectionRefs>JPS_FIADF12-3</JourneyPatternSectionRefs>
        </JourneyPattern>
        <JourneyPattern id="JPS_FIADF12-4">
          <Direction>outbound</Direction>
          <JourneyPatternSectionRefs>JPS_FIADF12-4</JourneyPatternSectionRefs>
        </JourneyPattern>
      </StandardService>
    </Service>
  </Services>
  <VehicleJourneys>
    <VehicleJourney>
      <OperatorRef>SIF</OperatorRef>
      <OperatingProfile>
        <RegularDayType>
          <DaysOfWeek>
            <Monday />
            <Tuesday />
          </DaysOfWeek>
        </RegularDayType>
        <ServicedOrganisationDayType>
          <DaysOfNonOperation>
            <WorkingDays>
              <ServicedOrganisationRef>434</ServicedOrganisationRef>
            </WorkingDays>
          </DaysOfNonOperation>
        </ServicedOrganisationDayType>
      </OperatingProfile>
      <VehicleJourneyCode>23474</VehicleJourneyCode>
      <ServiceRef>FIADF12</ServiceRef>
      <LineRef>0</LineRef>
      <JourneyPatternRef>JPS_FIADF12-3</JourneyPatternRef>
      <DepartureTime>15:35:00</DepartureTime>
    </VehicleJourney>
    <VehicleJourney>
      <OperatorRef>SIF</OperatorRef>
      <OperatingProfile>
        <RegularDayType>
          <DaysOfWeek>
            <Wednesday />
            <Thursday />
            <Friday />
          </DaysOfWeek>
        </RegularDayType>
        <ServicedOrganisationDayType>
          <DaysOfNonOperation>
            <WorkingDays>
              <ServicedOrganisationRef>435</ServicedOrganisationRef>
            </WorkingDays>
          </DaysOfNonOperation>
        </ServicedOrganisationDayType>
      </OperatingProfile>
      <VehicleJourneyCode>23475</VehicleJourneyCode>
      <ServiceRef>FIADF12</ServiceRef>
      <LineRef>0</LineRef>
      <JourneyPatternRef>JPS_FIADF12-3</JourneyPatternRef>
      <DepartureTime>14:45:00</DepartureTime>
    </VehicleJourney>
    <VehicleJourney>
      <OperatorRef>SIF</OperatorRef>
      <OperatingProfile>
        <RegularDayType>
          <DaysOfWeek>
            <Monday />
            <Tuesday />
            <Wednesday />
            <Thursday />
            <Friday />
          </DaysOfWeek>
        </RegularDayType>
        <ServicedOrganisationDayType>
          <DaysOfNonOperation>
            <WorkingDays>
              <ServicedOrganisationRef>436</ServicedOrganisationRef>
            </WorkingDays>
          </DaysOfNonOperation>
        </ServicedOrganisationDayType>
      </OperatingProfile>
      <VehicleJourneyCode>23476</VehicleJourneyCode>
      <ServiceRef>FIADF12</ServiceRef>
      <LineRef>0</LineRef>
      <JourneyPatternRef>JPS_FIADF12-4</JourneyPatternRef>
      <DepartureTime>07:52:00</DepartureTime>
    </VehicleJourney>
  </VehicleJourneys>
</TransXChange>