<?xml version="1.0" encoding="utf-8"?>
<TransXChange xmlns:xsi="http://www.w3.org/2001/XMLSchema-instance" xmlns:xsd="http://www.w3.org/2001/XMLSchema" xsi:schemaLocation="http://www.transxchange.org.uk/ http://www.transxchange.org.uk/schema/2.1/TransXChange_general.xsd" CreationDateTime="2019-10-07T12:17:00-00:00" ModificationDateTime="2019-10-07T12:17:00-00:00" Modification="new" RevisionNumber="0" FileName="SVRSLAO012F.xml" SchemaVersion="2.1" RegistrationDocument="false" xmlns="http://www.transxchange.org.uk/">
  <StopPoints>
    <AnnotatedStopPointRef>
      <StopPointRef>6030457</StopPointRef>
      <CommonName>Whitelaw Road</CommonName>
    </AnnotatedStopPointRef>
    <AnnotatedStopPointRef>
      <StopPointRef>603047</StopPointRef>
      <CommonName>Playing Field</CommonName>
    </AnnotatedStopPointRef>
    <AnnotatedStopPointRef>
      <StopPointRef>6030455</StopPointRef>
      <CommonName>Post Office</CommonName>
    </AnnotatedStopPointRef>
    <AnnotatedStopPointRef>
      <StopPointRef>6030243</StopPointRef>
      <CommonName>Biggings</CommonName>
    </AnnotatedStopPointRef>
    <AnnotatedStopPointRef>
      <StopPointRef>6030459</StopPointRef>
      <CommonName>Kelda Lea</CommonName>
    </AnnotatedStopPointRef>
    <AnnotatedStopPointRef>
      <StopPointRef>6030461</StopPointRef>
      <CommonName>Varshjem</CommonName>
    </AnnotatedStopPointRef>
    <AnnotatedStopPointRef>
      <StopPointRef>6030242</StopPointRef>
      <CommonName>Road End</CommonName>
    </AnnotatedStopPointRef>
    <AnnotatedStopPointRef>
      <StopPointRef>6030710063</StopPointRef>
      <CommonName>Post Office</CommonName>
    </AnnotatedStopPointRef>
    <AnnotatedStopPointRef>
      <StopPointRef>6030261</StopPointRef>
      <CommonName>Health Centre</CommonName>
    </AnnotatedStopPointRef>
    <AnnotatedStopPointRef>
      <StopPointRef>6030223</StopPointRef>
      <CommonName>Health Centre</CommonName>
    </AnnotatedStopPointRef>
    <AnnotatedStopPointRef>
      <StopPointRef>6030224</StopPointRef>
      <CommonName>Post Office</CommonName>
    </AnnotatedStopPointRef>
    <AnnotatedStopPointRef>
      <StopPointRef>603045</StopPointRef>
      <CommonName>Road End</CommonName>
    </AnnotatedStopPointRef>
    <AnnotatedStopPointRef>
      <StopPointRef>6030460</StopPointRef>
      <CommonName>Varshjem</CommonName>
    </AnnotatedStopPointRef>
    <AnnotatedStopPointRef>
      <StopPointRef>6030458</StopPointRef>
      <CommonName>Kelda Lea</CommonName>
    </AnnotatedStopPointRef>
    <AnnotatedStopPointRef>
      <StopPointRef>603046</StopPointRef>
      <CommonName>Biggings</CommonName>
    </AnnotatedStopPointRef>
    <AnnotatedStopPointRef>
      <StopPointRef>6030710069</StopPointRef>
      <CommonName>Post Office</CommonName>
    </AnnotatedStopPointRef>
    <AnnotatedStopPointRef>
      <StopPointRef>6030456</StopPointRef>
      <CommonName>Playing Field</CommonName>
    </AnnotatedStopPointRef>
  </StopPoints>
  <RouteSections>
    <RouteSection id="SLAO012F002">
      <RouteLink id="SLAO012F002_195898">
        <From>
          <StopPointRef>6030457</StopPointRef>
        </From>
        <To>
          <StopPointRef>603047</StopPointRef>
        </To>
        <Direction>inbound</Direction>
      </RouteLink>
      <RouteLink id="SLAO012F002_195899">
        <From>
          <StopPointRef>603047</StopPointRef>
        </From>
        <To>
          <StopPointRef>6030455</StopPointRef>
        </To>
        <Direction>inbound</Direction>
      </RouteLink>
      <RouteLink id="SLAO012F002_195900">
        <From>
          <StopPointRef>6030455</StopPointRef>
        </From>
        <To>
          <StopPointRef>6030243</StopPointRef>
        </To>
        <Direction>inbound</Direction>
      </RouteLink>
      <RouteLink id="SLAO012F002_195901">
        <From>
          <StopPointRef>6030243</StopPointRef>
        </From>
        <To>
          <StopPointRef>6030459</StopPointRef>
        </To>
        <Direction>inbound</Direction>
      </RouteLink>
      <RouteLink id="SLAO012F002_195902">
        <From>
          <StopPointRef>6030459</StopPointRef>
        </From>
        <To>
          <StopPointRef>6030461</StopPointRef>
        </To>
        <Direction>inbound</Direction>
      </RouteLink>
      <RouteLink id="SLAO012F002_195903">
        <From>
          <StopPointRef>6030461</StopPointRef>
        </From>
        <To>
          <StopPointRef>6030242</StopPointRef>
        </To>
        <Direction>inbound</Direction>
      </RouteLink>
      <RouteLink id="SLAO012F002_195904">
        <From>
          <StopPointRef>6030242</StopPointRef>
        </From>
        <To>
          <StopPointRef>6030710063</StopPointRef>
        </To>
        <Direction>inbound</Direction>
      </RouteLink>
      <RouteLink id="SLAO012F002_195905">
        <From>
          <StopPointRef>6030710063</StopPointRef>
        </From>
        <To>
          <StopPointRef>6030261</StopPointRef>
        </To>
        <Direction>inbound</Direction>
      </RouteLink>
    </RouteSection>
    <RouteSection id="SLAO012F001">
      <RouteLink id="SLAO012F001_195907">
        <From>
          <StopPointRef>6030223</StopPointRef>
        </From>
        <To>
          <StopPointRef>6030224</StopPointRef>
        </To>
        <Direction>outbound</Direction>
      </RouteLink>
      <RouteLink id="SLAO012F001_195908">
        <From>
          <StopPointRef>6030224</StopPointRef>
        </From>
        <To>
          <StopPointRef>603045</StopPointRef>
        </To>
        <Direction>outbound</Direction>
      </RouteLink>
      <RouteLink id="SLAO012F001_195909">
        <From>
          <StopPointRef>603045</StopPointRef>
        </From>
        <To>
          <StopPointRef>6030460</StopPointRef>
        </To>
        <Direction>outbound</Direction>
      </RouteLink>
      <RouteLink id="SLAO012F001_195910">
        <From>
          <StopPointRef>6030460</StopPointRef>
        </From>
        <To>
          <StopPointRef>6030458</StopPointRef>
        </To>
        <Direction>outbound</Direction>
      </RouteLink>
      <RouteLink id="SLAO012F001_195911">
        <From>
          <StopPointRef>6030458</StopPointRef>
        </From>
        <To>
          <StopPointRef>603046</StopPointRef>
        </To>
        <Direction>outbound</Direction>
      </RouteLink>
      <RouteLink id="SLAO012F001_195912">
        <From>
          <StopPointRef>603046</StopPointRef>
        </From>
        <To>
          <StopPointRef>6030710069</StopPointRef>
        </To>
        <Direction>outbound</Direction>
      </RouteLink>
      <RouteLink id="SLAO012F001_195913">
        <From>
          <StopPointRef>6030710069</StopPointRef>
        </From>
        <To>
          <StopPointRef>6030456</StopPointRef>
        </To>
        <Direction>outbound</Direction>
      </RouteLink>
      <RouteLink id="SLAO012F001_195914">
        <From>
          <StopPointRef>6030456</StopPointRef>
        </From>
        <To>
          <StopPointRef>6030457</StopPointRef>
        </To>
        <Direction>outbound</Direction>
      </RouteLink>
    </RouteSection>
  </RouteSections>
  <Routes>
    <Route id="SLAO012F002">
      <Description>Aith - Bixter
</Description>
      <RouteSectionRef>SLAO012F002</RouteSectionRef>
    </Route>
    <Route id="SLAO012F001">
      <Description>Bixter - Aith
</Description>
      <RouteSectionRef>SLAO012F001</RouteSectionRef>
    </Route>
  </Routes>
  <JourneyPatternSections>
    <JourneyPatternSection id="JPS_SLAO012F-3">
      <JourneyPatternTimingLink id="JPS_SLAO012F-3_195898">
        <From>
          <StopPointRef>6030457</StopPointRef>
          <TimingStatus>PTP</TimingStatus>
        </From>
        <To>
          <StopPointRef>603047</StopPointRef>
          <TimingStatus>OTH</TimingStatus>
        </To>
        <RouteLinkRef>SLAO012F002_195898</RouteLinkRef>
        <Direction>inbound</Direction>
        <RunTime>PT0S</RunTime>
      </JourneyPatternTimingLink>
      <JourneyPatternTimingLink id="JPS_SLAO012F-3_195899">
        <From>
          <StopPointRef>603047</StopPointRef>
          <TimingStatus>OTH</TimingStatus>
        </From>
        <To>
          <StopPointRef>6030455</StopPointRef>
          <TimingStatus>OTH</TimingStatus>
        </To>
        <RouteLinkRef>SLAO012F002_195899</RouteLinkRef>
        <Direction>inbound</Direction>
        <RunTime>PT0S</RunTime>
      </JourneyPatternTimingLink>
      <JourneyPatternTimingLink id="JPS_SLAO012F-3_195900">
        <From>
          <StopPointRef>6030455</StopPointRef>
          <TimingStatus>OTH</TimingStatus>
        </From>
        <To>
          <StopPointRef>6030243</StopPointRef>
          <TimingStatus>OTH</TimingStatus>
        </To>
        <RouteLinkRef>SLAO012F002_195900</RouteLinkRef>
        <Direction>inbound</Direction>
        <RunTime>PT60S</RunTime>
      </JourneyPatternTimingLink>
      <JourneyPatternTimingLink id="JPS_SLAO012F-3_195901">
        <From>
          <StopPointRef>6030243</StopPointRef>
          <TimingStatus>OTH</TimingStatus>
        </From>
        <To>
          <StopPointRef>6030459</StopPointRef>
          <TimingStatus>OTH</TimingStatus>
        </To>
        <RouteLinkRef>SLAO012F002_195901</RouteLinkRef>
        <Direction>inbound</Direction>
        <RunTime>PT0S</RunTime>
      </JourneyPatternTimingLink>
      <JourneyPatternTimingLink id="JPS_SLAO012F-3_195902">
        <From>
          <StopPointRef>6030459</StopPointRef>
          <TimingStatus>OTH</TimingStatus>
        </From>
        <To>
          <StopPointRef>6030461</StopPointRef>
          <TimingStatus>OTH</TimingStatus>
        </To>
        <RouteLinkRef>SLAO012F002_195902</RouteLinkRef>
        <Direction>inbound</Direction>
        <RunTime>PT60S</RunTime>
      </JourneyPatternTimingLink>
      <JourneyPatternTimingLink id="JPS_SLAO012F-3_195903">
        <From>
          <StopPointRef>6030461</StopPointRef>
          <TimingStatus>OTH</TimingStatus>
        </From>
        <To>
          <StopPointRef>6030242</StopPointRef>
          <TimingStatus>OTH</TimingStatus>
        </To>
        <RouteLinkRef>SLAO012F002_195903</RouteLinkRef>
        <Direction>inbound</Direction>
        <RunTime>PT240S</RunTime>
      </JourneyPatternTimingLink>
      <JourneyPatternTimingLink id="JPS_SLAO012F-3_195904">
        <From>
          <StopPointRef>6030242</StopPointRef>
          <TimingStatus>OTH</TimingStatus>
        </From>
        <To>
          <StopPointRef>6030710063</StopPointRef>
          <TimingStatus>OTH</TimingStatus>
        </To>
        <RouteLinkRef>SLAO012F002_195904</RouteLinkRef>
        <Direction>inbound</Direction>
        <RunTime>PT60S</RunTime>
      </JourneyPatternTimingLink>
      <JourneyPatternTimingLink id="JPS_SLAO012F-3_195905">
        <From>
          <StopPointRef>6030710063</StopPointRef>
          <TimingStatus>OTH</TimingStatus>
        </From>
        <To>
          <StopPointRef>6030261</StopPointRef>
          <TimingStatus>PTP</TimingStatus>
        </To>
        <RouteLinkRef>SLAO012F002_195905</RouteLinkRef>
        <Direction>inbound</Direction>
        <RunTime>PT60S</RunTime>
      </JourneyPatternTimingLink>
    </JourneyPatternSection>
    <JourneyPatternSection id="JPS_SLAO012F-4">
      <JourneyPatternTimingLink id="JPS_SLAO012F-4_195907">
        <From>
          <StopPointRef>6030223</StopPointRef>
          <TimingStatus>PTP</TimingStatus>
        </From>
        <To>
          <StopPointRef>6030224</StopPointRef>
          <TimingStatus>OTH</TimingStatus>
        </To>
        <RouteLinkRef>SLAO012F001_195907</RouteLinkRef>
        <Direction>outbound</Direction>
        <RunTime>PT0S</RunTime>
      </JourneyPatternTimingLink>
      <JourneyPatternTimingLink id="JPS_SLAO012F-4_195908">
        <From>
          <StopPointRef>6030224</StopPointRef>
          <TimingStatus>OTH</TimingStatus>
        </From>
        <To>
          <StopPointRef>603045</StopPointRef>
          <TimingStatus>OTH</TimingStatus>
        </To>
        <RouteLinkRef>SLAO012F001_195908</RouteLinkRef>
        <Direction>outbound</Direction>
        <RunTime>PT60S</RunTime>
      </JourneyPatternTimingLink>
      <JourneyPatternTimingLink id="JPS_SLAO012F-4_195909">
        <From>
          <StopPointRef>603045</StopPointRef>
          <TimingStatus>OTH</TimingStatus>
        </From>
        <To>
          <StopPointRef>6030460</StopPointRef>
          <TimingStatus>OTH</TimingStatus>
        </To>
        <RouteLinkRef>SLAO012F001_195909</RouteLinkRef>
        <Direction>outbound</Direction>
        <RunTime>PT240S</RunTime>
      </JourneyPatternTimingLink>
      <JourneyPatternTimingLink id="JPS_SLAO012F-4_195910">
        <From>
          <StopPointRef>6030460</StopPointRef>
          <TimingStatus>OTH</TimingStatus>
        </From>
        <To>
          <StopPointRef>6030458</StopPointRef>
          <TimingStatus>OTH</TimingStatus>
        </To>
        <RouteLinkRef>SLAO012F001_195910</RouteLinkRef>
        <Direction>outbound</Direction>
        <RunTime>PT60S</RunTime>
      </JourneyPatternTimingLink>
      <JourneyPatternTimingLink id="JPS_SLAO012F-4_195911">
        <From>
          <StopPointRef>6030458</StopPointRef>
          <TimingStatus>OTH</TimingStatus>
        </From>
        <To>
          <StopPointRef>603046</StopPointRef>
          <TimingStatus>OTH</TimingStatus>
        </To>
        <RouteLinkRef>SLAO012F001_195911</RouteLinkRef>
        <Direction>outbound</Direction>
        <RunTime>PT0S</RunTime>
      </JourneyPatternTimingLink>
      <JourneyPatternTimingLink id="JPS_SLAO012F-4_195912">
        <From>
          <StopPointRef>603046</StopPointRef>
          <TimingStatus>OTH</TimingStatus>
        </From>
        <To>
          <StopPointRef>6030710069</StopPointRef>
          <TimingStatus>OTH</TimingStatus>
        </To>
        <RouteLinkRef>SLAO012F001_195912</RouteLinkRef>
        <Direction>outbound</Direction>
        <RunTime>PT60S</RunTime>
      </JourneyPatternTimingLink>
      <JourneyPatternTimingLink id="JPS_SLAO012F-4_195913">
        <From>
          <StopPointRef>6030710069</StopPointRef>
          <TimingStatus>OTH</TimingStatus>
        </From>
        <To>
          <StopPointRef>6030456</StopPointRef>
          <TimingStatus>OTH</TimingStatus>
        </To>
        <RouteLinkRef>SLAO012F001_195913</RouteLinkRef>
        <Direction>outbound</Direction>
        <RunTime>PT0S</RunTime>
      </JourneyPatternTimingLink>
      <JourneyPatternTimingLink id="JPS_SLAO012F-4_195914">
        <From>
          <StopPointRef>6030456</StopPointRef>
          <TimingStatus>OTH</TimingStatus>
        </From>
        <To>
          <StopPointRef>6030457</StopPointRef>
          <TimingStatus>PTP</TimingStatus>
        </To>
        <RouteLinkRef>SLAO012F001_195914</RouteLinkRef>
        <Direction>outbound</Direction>
        <RunTime>PT60S</RunTime>
      </JourneyPatternTimingLink>
    </JourneyPatternSection>
  </JourneyPatternSections>
  <Operators>
    <Operator id="WST">
      <NationalOperatorCode>WSTS</NationalOperatorCode>
      <OperatorCode>WST</OperatorCode>
      <OperatorShortName>Wastbus</OperatorShortName>
    </Operator>
    <Operator id="SIC">
      <NationalOperatorCode>SHIC</NationalOperatorCode>
      <OperatorCode>SIC</OperatorCode>
      <OperatorShortName>Shetland Islands Council</OperatorShortName>
    </Operator>
  </Operators>
  <Services>
    <Service>
      <ServiceCode>SLAO012F</ServiceCode>
      <Lines>
        <Line id="0">
          <LineName>12F</LineName>
        </Line>
      </Lines>
      <OperatingPeriod>
        <StartDate>2014-08-18</StartDate>
        <EndDate>2049-12-31</EndDate>
      </OperatingPeriod>
      <RegisteredOperatorRef>WST</RegisteredOperatorRef>
      <StopRequirements>
        <NoNewStopsRequired />
      </StopRequirements>
      <Mode>bus</Mode>
      <Description>Bixter - Aith</Description>
      <StandardService>
        <Origin>Bixter</Origin>
        <Destination>Aith</Destination>
        <JourneyPattern id="JPS_SLAO012F-3">
          <Direction>inbound</Direction>
          <JourneyPatternSectionRefs>JPS_SLAO012F-3</JourneyPatternSectionRefs>
        </JourneyPattern>
        <JourneyPattern id="JPS_SLAO012F-4">
          <Direction>outbound</Direction>
          <JourneyPatternSectionRefs>JPS_SLAO012F-4</JourneyPatternSectionRefs>
        </JourneyPattern>
      </StandardService>
    </Service>
  </Services>
  <VehicleJourneys>
    <VehicleJourney>
      <OperatorRef>WST</OperatorRef>
      <OperatingProfile>
        <RegularDayType>
          <DaysOfWeek>
            <Monday />
            <Tuesday />
            <Wednesday />
            <Thursday />
            <Friday />
          </DaysOfWeek>
        </RegularDayType>
      </OperatingProfile>
      <VehicleJourneyCode>57615</VehicleJourneyCode>
      <ServiceRef>SLAO012F</ServiceRef>
      <LineRef>0</LineRef>
      <JourneyPatternRef>JPS_SLAO012F-3</JourneyPatternRef>
      <DepartureTime>10:25:00</DepartureTime>
    </VehicleJourney>
    <VehicleJourney>
      <OperatorRef>WST</OperatorRef>
      <OperatingProfile>
        <RegularDayType>
          <DaysOfWeek>
            <Monday />
            <Tuesday />
            <Wednesday />
            <Thursday />
            <Friday />
          </DaysOfWeek>
        </RegularDayType>
      </OperatingProfile>
      <VehicleJourneyCode>57616</VehicleJourneyCode>
      <ServiceRef>SLAO012F</ServiceRef>
      <LineRef>0</LineRef>
      <JourneyPatternRef>JPS_SLAO012F-3</JourneyPatternRef>
      <DepartureTime>13:25:00</DepartureTime>
    </VehicleJourney>
    <VehicleJourney>
      <OperatorRef>WST</OperatorRef>
      <OperatingProfile>
        <RegularDayType>
          <DaysOfWeek>
            <Saturday />
          </DaysOfWeek>
        </RegularDayType>
      </OperatingProfile>
      <VehicleJourneyCode>57617</VehicleJourneyCode>
      <ServiceRef>SLAO012F</ServiceRef>
      <LineRef>0</LineRef>
      <JourneyPatternRef>JPS_SLAO012F-3</JourneyPatternRef>
      <DepartureTime>08:00:00</DepartureTime>
    </VehicleJourney>
    <VehicleJourney>
      <OperatorRef>WST</OperatorRef>
      <OperatingProfile>
        <RegularDayType>
          <DaysOfWeek>
            <Saturday />
          </DaysOfWeek>
        </RegularDayType>
      </OperatingProfile>
      <VehicleJourneyCode>57618</VehicleJourneyCode>
      <ServiceRef>SLAO012F</ServiceRef>
      <LineRef>0</LineRef>
      <JourneyPatternRef>JPS_SLAO012F-3</JourneyPatternRef>
      <DepartureTime>10:25:00</DepartureTime>
    </VehicleJourney>
    <VehicleJourney>
      <OperatorRef>WST</OperatorRef>
      <OperatingProfile>
        <RegularDayType>
          <DaysOfWeek>
            <Saturday />
          </DaysOfWeek>
        </RegularDayType>
      </OperatingProfile>
      <VehicleJourneyCode>57619</VehicleJourneyCode>
      <ServiceRef>SLAO012F</ServiceRef>
      <LineRef>0</LineRef>
      <JourneyPatternRef>JPS_SLAO012F-3</JourneyPatternRef>
      <DepartureTime>13:25:00</DepartureTime>
    </VehicleJourney>
    <VehicleJourney>
      <OperatorRef>WST</OperatorRef>
      <OperatingProfile>
        <RegularDayType>
          <DaysOfWeek>
            <Saturday />
          </DaysOfWeek>
        </RegularDayType>
      </OperatingProfile>
      <VehicleJourneyCode>57620</VehicleJourneyCode>
      <ServiceRef>SLAO012F</ServiceRef>
      <LineRef>0</LineRef>
      <JourneyPatternRef>JPS_SLAO012F-3</JourneyPatternRef>
      <DepartureTime>16:25:00</DepartureTime>
    </VehicleJourney>
    <VehicleJourney>
      <OperatorRef>WST</OperatorRef>
      <OperatingProfile>
        <RegularDayType>
          <DaysOfWeek>
            <Monday />
            <Tuesday />
            <Wednesday />
            <Thursday />
            <Friday />
          </DaysOfWeek>
        </RegularDayType>
      </OperatingProfile>
      <VehicleJourneyCode>57621</VehicleJourneyCode>
      <ServiceRef>SLAO012F</ServiceRef>
      <LineRef>0</LineRef>
      <JourneyPatternRef>JPS_SLAO012F-4</JourneyPatternRef>
      <DepartureTime>12:58:00</DepartureTime>
    </VehicleJourney>
    <VehicleJourney>
      <OperatorRef>WST</OperatorRef>
      <OperatingProfile>
        <RegularDayType>
          <DaysOfWeek>
            <Saturday />
          </DaysOfWeek>
        </RegularDayType>
      </OperatingProfile>
      <VehicleJourneyCode>57622</VehicleJourneyCode>
      <ServiceRef>SLAO012F</ServiceRef>
      <LineRef>0</LineRef>
      <JourneyPatternRef>JPS_SLAO012F-4</JourneyPatternRef>
      <DepartureTime>12:58:00</DepartureTime>
    </VehicleJourney>
    <VehicleJourney>
      <OperatorRef>WST</OperatorRef>
      <OperatingProfile>
        <RegularDayType>
          <DaysOfWeek>
            <Saturday />
          </DaysOfWeek>
        </RegularDayType>
      </OperatingProfile>
      <VehicleJourneyCode>57623</VehicleJourneyCode>
      <ServiceRef>SLAO012F</ServiceRef>
      <LineRef>0</LineRef>
      <JourneyPatternRef>JPS_SLAO012F-4</JourneyPatternRef>
      <DepartureTime>15:58:00</DepartureTime>
    </VehicleJourney>
    <VehicleJourney>
      <OperatorRef>WST</OperatorRef>
      <OperatingProfile>
        <RegularDayType>
          <DaysOfWeek>
            <Saturday />
          </DaysOfWeek>
        </RegularDayType>
      </OperatingProfile>
      <VehicleJourneyCode>57624</VehicleJourneyCode>
      <ServiceRef>SLAO012F</ServiceRef>
      <LineRef>0</LineRef>
      <JourneyPatternRef>JPS_SLAO012F-4</JourneyPatternRef>
      <DepartureTime>17:52:00</DepartureTime>
    </VehicleJourney>
  </VehicleJourneys>
</TransXChange>